Workbook

Sheet Country
A1: Country | B1: Cost of Living | C1: Safety | D1: Healthcare | E1: Political Stability | F1: Pollution | G1: Climate | H1: English Proficiency | I1: Openness | J1: Natural Scenery | K1: Natural Disaster | L1: Life Expectancy at 60
A2: Switzerland | B2: =VLOOKUP(A2, Sheet1!A:B, 2, FALSE()) -> 81.5 | C2: =VLOOKUP(A2, Safety!A:B, 2, FALSE()) -> 89.234036 | D2: =VLOOKUP(A2, Health!A:B, 2, FALSE()) -> 68.8 | E2: =VLOOKUP(A2, Political!A:H, 8, FALSE()) -> 87.26 | F2: =VLOOKUP(A2, Pollution!A:B, 2, FALSE()) -> 8.32 | G2: =VLOOKUP(A2, Climate!A:B, 2, FALSE()) -> 2357 | H2: =VLOOKUP(A2, English!A:C, 3, FALSE()) -> 564 | I2: =VLOOKUP(A2, Openness!A:C, 2, FALSE()) -> 46 | J2: =VLOOKUP(A2, Scenic!A:B, 2, FALSE()) -> 4 | K2: =VLOOKUP(A2, Disaster!A:H, 4, FALSE()) -> 0.16 | L2: =VLOOKUP(A2, LifeExp60!A:B, 2, FALSE()) -> 27.468
A3: Luxembourg | B3: =VLOOKUP(A3, Sheet1!A:B, 2, FALSE()) -> 64.2 | C3: =VLOOKUP(A3, Safety!A:B, 2, FALSE()) -> 78.643759 | D3: =VLOOKUP(A3, Health!A:B, 2, FALSE()) -> 70.7 | E3: =VLOOKUP(A3, Political!A:H, 8, FALSE()) -> 87.306667 | F3: =VLOOKUP(A3, Pollution!A:B, 2, FALSE()) -> 7.43 | G3: =VLOOKUP(A3, Climate!A:B, 2, FALSE()) -> 2218 | H3: =VLOOKUP(A3, English!A:C, 3, FALSE()) -> 576 | I3: =VLOOKUP(A3, Openness!A:C, 2, FALSE()) -> 38 | J3: =VLOOKUP(A3, Scenic!A:B, 2, FALSE()) -> 40 | K3: =VLOOKUP(A3, Disaster!A:H, 4, FALSE()) -> 0.06 | L3: =VLOOKUP(A3, LifeExp60!A:B, 2, FALSE()) -> 26.17
A4: Iceland | B4: =VLOOKUP(A4, Sheet1!A:B, 2, FALSE()) -> 74.8 | C4: =VLOOKUP(A4, Safety!A:B, 2, FALSE()) -> 80.944996 | D4: =VLOOKUP(A4, Health!A:B, 2, FALSE()) -> 68.7 | E4: =VLOOKUP(A4, Political!A:H, 8, FALSE()) -> 83.221667 | F4: =VLOOKUP(A4, Pollution!A:B, 2, FALSE()) -> 4.93 | G4: =VLOOKUP(A4, Climate!A:B, 2, FALSE()) -> 1012 | H4: =VLOOKUP(A4, English!A:C, 3, FALSE()) -> #N/A | I4: =VLOOKUP(A4, Openness!A:C, 2, FALSE()) -> #N/A | J4: =VLOOKUP(A4, Scenic!A:B, 2, FALSE()) -> 8 | K4: =VLOOKUP(A4, Disaster!A:H, 4, FALSE()) -> 0.71 | L4: =VLOOKUP(A4, LifeExp60!A:B, 2, FALSE()) -> 25.948
A5: Singapore | B5: =VLOOKUP(A5, Sheet1!A:B, 2, FALSE()) -> 80.5 | C5: =VLOOKUP(A5, Safety!A:B, 2, FALSE()) -> 98.465492 | D5: =VLOOKUP(A5, Health!A:B, 2, FALSE()) -> 71.9 | E5: =VLOOKUP(A5, Political!A:H, 8, FALSE()) -> 83.598333 | F5: =VLOOKUP(A5, Pollution!A:B, 2, FALSE()) -> 15.14 | G5: =VLOOKUP(A5, Climate!A:B, 2, FALSE()) -> 1186 | H5: =VLOOKUP(A5, English!A:C, 3, FALSE()) -> 609 | I5: =VLOOKUP(A5, Openness!A:C, 2, FALSE()) -> 30 | J5: =VLOOKUP(A5, Scenic!A:B, 2, FALSE()) -> 33 | K5: =VLOOKUP(A5, Disaster!A:H, 4, FALSE()) -> 0.17 | L5: =VLOOKUP(A5, LifeExp60!A:B, 2, FALSE()) -> 27.825
A6: Norway | B6: =VLOOKUP(A6, Sheet1!A:B, 2, FALSE()) -> 59.3 | C6: =VLOOKUP(A6, Safety!A:B, 2, FALSE()) -> 87.460889 | D6: =VLOOKUP(A6, Health!A:B, 2, FALSE()) -> 75.1 | E6: =VLOOKUP(A6, Political!A:H, 8, FALSE()) -> 87.685 | F6: =VLOOKUP(A6, Pollution!A:B, 2, FALSE()) -> 5.52 | G6: =VLOOKUP(A6, Climate!A:B, 2, FALSE()) -> 1821 | H6: =VLOOKUP(A6, English!A:C, 3, FALSE()) -> 613 | I6: =VLOOKUP(A6, Openness!A:C, 2, FALSE()) -> 52 | J6: =VLOOKUP(A6, Scenic!A:B, 2, FALSE()) -> 7 | K6: =VLOOKUP(A6, Disaster!A:H, 4, FALSE()) -> 1.1 | L6: =VLOOKUP(A6, LifeExp60!A:B, 2, FALSE()) -> 26.522
A7: United States | B7: =VLOOKUP(A7, Sheet1!A:B, 2, FALSE()) -> 54.8 | C7: =VLOOKUP(A7, Safety!A:B, 2, FALSE()) -> 56.040163 | D7: =VLOOKUP(A7, Health!A:B, 2, FALSE()) -> 66.9 | E7: =VLOOKUP(A7, Political!A:H, 8, FALSE()) -> 69.428333 | F7: =VLOOKUP(A7, Pollution!A:B, 2, FALSE()) -> 6.97 | G7: =VLOOKUP(A7, Climate!A:B, 2, FALSE()) -> 2418 | H7: 700 | I7: =VLOOKUP(A7, Openness!A:C, 2, FALSE()) -> 28 | J7: =VLOOKUP(A7, Scenic!A:B, 2, FALSE()) -> 51 | K7: =VLOOKUP(A7, Disaster!A:H, 4, FALSE()) -> 39.78 | L7: =VLOOKUP(A7, LifeExp60!A:B, 2, FALSE()) -> 25.365
A8: Denmark | B8: =VLOOKUP(A8, Sheet1!A:B, 2, FALSE()) -> 54.8 | C8: =VLOOKUP(A8, Safety!A:B, 2, FALSE()) -> 85.964139 | D8: =VLOOKUP(A8, Health!A:B, 2, FALSE()) -> 74.4 | E8: =VLOOKUP(A8, Political!A:H, 8, FALSE()) -> 88.74 | F8: =VLOOKUP(A8, Pollution!A:B, 2, FALSE()) -> 7.5 | G8: =VLOOKUP(A8, Climate!A:B, 2, FALSE()) -> 1961 | H8: =VLOOKUP(A8, English!A:C, 3, FALSE()) -> 611 | I8: =VLOOKUP(A8, Openness!A:C, 2, FALSE()) -> 45 | J8: =VLOOKUP(A8, Scenic!A:B, 2, FALSE()) -> 25 | K8: =VLOOKUP(A8, Disaster!A:H, 4, FALSE()) -> 0.18 | L8: =VLOOKUP(A8, LifeExp60!A:B, 2, FALSE()) -> 25.735
A9: Qatar | B9: =VLOOKUP(A9, Sheet1!A:B, 2, FALSE()) -> 44.1 | C9: =VLOOKUP(A9, Safety!A:B, 2, FALSE()) -> 98.465492 | D9: =VLOOKUP(A9, Health!A:B, 2, FALSE()) -> 73.8 | E9: =VLOOKUP(A9, Political!A:H, 8, FALSE()) -> 66.15 | F9: =VLOOKUP(A9, Pollution!A:B, 2, FALSE()) -> 107.76 | G9: =VLOOKUP(A9, Climate!A:B, 2, FALSE()) -> 1851 | H9: =VLOOKUP(A9, English!A:C, 3, FALSE()) -> 469 | I9: =VLOOKUP(A9, Openness!A:C, 2, FALSE()) -> 22 | J9: =VLOOKUP(A9, Scenic!A:B, 2, FALSE()) -> 69 | K9: =VLOOKUP(A9, Disaster!A:H, 4, FALSE()) -> 0.17 | L9: =VLOOKUP(A9, LifeExp60!A:B, 2, FALSE()) -> 25.209
A10: Australia | B10: =VLOOKUP(A10, Sheet1!A:B, 2, FALSE()) -> 53.9 | C10: =VLOOKUP(A10, Safety!A:B, 2, FALSE()) -> 85.802312 | D10: =VLOOKUP(A10, Health!A:B, 2, FALSE()) -> 71.8 | E10: =VLOOKUP(A10, Political!A:H, 8, FALSE()) -> 83.875 | F10: =VLOOKUP(A10, Pollution!A:B, 2, FALSE()) -> 6.41 | G10: =VLOOKUP(A10, Climate!A:B, 2, FALSE()) -> 3315 | H10: 700 | I10: =VLOOKUP(A10, Openness!A:C, 2, FALSE()) -> 20 | J10: =VLOOKUP(A10, Scenic!A:B, 2, FALSE()) -> 9 | K10: =VLOOKUP(A10, Disaster!A:H, 4, FALSE()) -> 32.11 | L10: =VLOOKUP(A10, LifeExp60!A:B, 2, FALSE()) -> 27.677
A11: Netherlands | B11: =VLOOKUP(A11, Sheet1!A:B, 2, FALSE()) -> 56 | C11: =VLOOKUP(A11, Safety!A:B, 2, FALSE()) -> 87.918709 | D11: =VLOOKUP(A11, Health!A:B, 2, FALSE()) -> 77.6 | E11: =VLOOKUP(A11, Political!A:H, 8, FALSE()) -> 83.676667 | F11: =VLOOKUP(A11, Pollution!A:B, 2, FALSE()) -> 8.59 | G11: =VLOOKUP(A11, Climate!A:B, 2, FALSE()) -> 2185 | H11: =VLOOKUP(A11, English!A:C, 3, FALSE()) -> 624 | I11: =VLOOKUP(A11, Openness!A:C, 2, FALSE()) -> 41 | J11: =VLOOKUP(A11, Scenic!A:B, 2, FALSE()) -> 21 | K11: =VLOOKUP(A11, Disaster!A:H, 4, FALSE()) -> 2.17 | L11: =VLOOKUP(A11, LifeExp60!A:B, 2, FALSE()) -> 25.753
A12: Israel | B12: =VLOOKUP(A12, Sheet1!A:B, 2, FALSE()) -> 64.8 | C12: =VLOOKUP(A12, Safety!A:B, 2, FALSE()) -> 77.796346 | D12: =VLOOKUP(A12, Health!A:B, 2, FALSE()) -> 73.5 | E12: =VLOOKUP(A12, Political!A:H, 8, FALSE()) -> 67.205 | F12: =VLOOKUP(A12, Pollution!A:B, 2, FALSE()) -> 21.9 | G12: =VLOOKUP(A12, Climate!A:B, 2, FALSE()) -> 2897 | H12: =VLOOKUP(A12, English!A:C, 3, FALSE()) -> 524 | I12: =VLOOKUP(A12, Openness!A:C, 2, FALSE()) -> #N/A | J12: =VLOOKUP(A12, Scenic!A:B, 2, FALSE()) -> 87 | K12: =VLOOKUP(A12, Disaster!A:H, 4, FALSE()) -> 1.2 | L12: =VLOOKUP(A12, LifeExp60!A:B, 2, FALSE()) -> 26.441
A13: United Kingdom | B13: =VLOOKUP(A13, Sheet1!A:B, 2, FALSE()) -> 50.8 | C13: =VLOOKUP(A13, Safety!A:B, 2, FALSE()) -> 82.729812 | D13: =VLOOKUP(A13, Health!A:B, 2, FALSE()) -> 72.4 | E13: =VLOOKUP(A13, Political!A:H, 8, FALSE()) -> 78.106667 | F13: =VLOOKUP(A13, Pollution!A:B, 2, FALSE()) -> 9.46 | G13: =VLOOKUP(A13, Climate!A:B, 2, FALSE()) -> 2219 | H13: 700 | I13: =VLOOKUP(A13, Openness!A:C, 2, FALSE()) -> 42 | J13: =VLOOKUP(A13, Scenic!A:B, 2, FALSE()) -> 45 | K13: =VLOOKUP(A13, Disaster!A:H, 4, FALSE()) -> 2.6 | L13: =VLOOKUP(A13, LifeExp60!A:B, 2, FALSE()) -> 25.596
A14: Ireland | B14: =VLOOKUP(A14, Sheet1!A:B, 2, FALSE()) -> 57.4 | C14: =VLOOKUP(A14, Safety!A:B, 2, FALSE()) -> 88.427504 | D14: =VLOOKUP(A14, Health!A:B, 2, FALSE()) -> 51.3 | E14: =VLOOKUP(A14, Political!A:H, 8, FALSE()) -> 82.925 | F14: =VLOOKUP(A14, Pollution!A:B, 2, FALSE()) -> 7.51 | G14: =VLOOKUP(A14, Climate!A:B, 2, FALSE()) -> 2068 | H14: 700 | I14: =VLOOKUP(A14, Openness!A:C, 2, FALSE()) -> 29 | J14: =VLOOKUP(A14, Scenic!A:B, 2, FALSE()) -> 11 | K14: =VLOOKUP(A14, Disaster!A:H, 4, FALSE()) -> 1.48 | L14: =VLOOKUP(A14, LifeExp60!A:B, 2, FALSE()) -> 26.357
A15: Germany | B15: =VLOOKUP(A15, Sheet1!A:B, 2, FALSE()) -> 47 | C15: =VLOOKUP(A15, Safety!A:B, 2, FALSE()) -> 85.105906 | D15: =VLOOKUP(A15, Health!A:B, 2, FALSE()) -> 71.3 | E15: =VLOOKUP(A15, Political!A:H, 8, FALSE()) -> 80.246667 | F15: =VLOOKUP(A15, Pollution!A:B, 2, FALSE()) -> 8.81 | G15: =VLOOKUP(A15, Climate!A:B, 2, FALSE()) -> 2327 | H15: =VLOOKUP(A15, English!A:C, 3, FALSE()) -> 615 | I15: =VLOOKUP(A15, Openness!A:C, 2, FALSE()) -> 51 | J15: =VLOOKUP(A15, Scenic!A:B, 2, FALSE()) -> 50 | K15: =VLOOKUP(A15, Disaster!A:H, 4, FALSE()) -> 1.95 | L15: =VLOOKUP(A15, LifeExp60!A:B, 2, FALSE()) -> 25.805
A16: Hong Kong (China) | B16: =VLOOKUP(A16, Sheet1!A:B, 2, FALSE()) -> 68.5 | C16: =VLOOKUP(A16, Safety!A:B, 2, FALSE()) -> 92.659493 | D16: =VLOOKUP(A16, Health!A:B, 2, FALSE()) -> 66.5 | E16: =VLOOKUP(A16, Political!A:H, 8, FALSE()) -> 74.946667 | F16: =VLOOKUP(A16, Pollution!A:B, 2, FALSE()) -> #N/A | G16: =VLOOKUP(A16, Climate!A:B, 2, FALSE()) -> #N/A | H16: =VLOOKUP(A16, English!A:C, 3, FALSE()) -> 538 | I16: =VLOOKUP(A16, Openness!A:C, 2, FALSE()) -> 27 | J16: =VLOOKUP(A16, Scenic!A:B, 2, FALSE()) -> #N/A | K16: =VLOOKUP(A16, Disaster!A:H, 4, FALSE()) -> #N/A | L16: =VLOOKUP(A16, LifeExp60!A:B, 2, FALSE()) -> 29.811
A17: Kuwait | B17: =VLOOKUP(A17, Sheet1!A:B, 2, FALSE()) -> 33.3 | C17: =VLOOKUP(A17, Safety!A:B, 2, FALSE()) -> 94.868153 | D17: =VLOOKUP(A17, Health!A:B, 2, FALSE()) -> 58.6 | E17: =VLOOKUP(A17, Political!A:H, 8, FALSE()) -> 58.123333 | F17: =VLOOKUP(A17, Pollution!A:B, 2, FALSE()) -> 62.35 | G17: =VLOOKUP(A17, Climate!A:B, 2, FALSE()) -> 2087 | H17: =VLOOKUP(A17, English!A:C, 3, FALSE()) -> 455 | I17: =VLOOKUP(A17, Openness!A:C, 2, FALSE()) -> 53 | J17: =VLOOKUP(A17, Scenic!A:B, 2, FALSE()) -> 88 | K17: =VLOOKUP(A17, Disaster!A:H, 4, FALSE()) -> 1.01 | L17: =VLOOKUP(A17, LifeExp60!A:B, 2, FALSE()) -> 23.704
A18: Austria | B18: =VLOOKUP(A18, Sheet1!A:B, 2, FALSE()) -> 49.3 | C18: =VLOOKUP(A18, Safety!A:B, 2, FALSE()) -> 85.531019 | D18: =VLOOKUP(A18, Health!A:B, 2, FALSE()) -> 77.5 | E18: =VLOOKUP(A18, Political!A:H, 8, FALSE()) -> 79.438333 | F18: =VLOOKUP(A18, Pollution!A:B, 2, FALSE()) -> 10.03 | G18: =VLOOKUP(A18, Climate!A:B, 2, FALSE()) -> 2382 | H18: =VLOOKUP(A18, English!A:C, 3, FALSE()) -> 616 | I18: =VLOOKUP(A18, Openness!A:C, 2, FALSE()) -> 49 | J18: =VLOOKUP(A18, Scenic!A:B, 2, FALSE()) -> 10 | K18: =VLOOKUP(A18, Disaster!A:H, 4, FALSE()) -> 0.16 | L18: =VLOOKUP(A18, LifeExp60!A:B, 2, FALSE()) -> 26.2
A19: Sweden | B19: =VLOOKUP(A19, Sheet1!A:B, 2, FALSE()) -> 44.7 | C19: =VLOOKUP(A19, Safety!A:B, 2, FALSE()) -> 82.427912 | D19: =VLOOKUP(A19, Health!A:B, 2, FALSE()) -> 68.1 | E19: =VLOOKUP(A19, Political!A:H, 8, FALSE()) -> 85.838333 | F19: =VLOOKUP(A19, Pollution!A:B, 2, FALSE()) -> 5.26 | G19: =VLOOKUP(A19, Climate!A:B, 2, FALSE()) -> 1962 | H19: =VLOOKUP(A19, English!A:C, 3, FALSE()) -> 609 | I19: =VLOOKUP(A19, Openness!A:C, 2, FALSE()) -> 48 | J19: =VLOOKUP(A19, Scenic!A:B, 2, FALSE()) -> 14 | K19: =VLOOKUP(A19, Disaster!A:H, 4, FALSE()) -> 1.07 | L19: =VLOOKUP(A19, LifeExp60!A:B, 2, FALSE()) -> 26.737
A20: Belgium | B20: =VLOOKUP(A20, Sheet1!A:B, 2, FALSE()) -> 47.2 | C20: =VLOOKUP(A20, Safety!A:B, 2, FALSE()) -> 83.157031 | D20: =VLOOKUP(A20, Health!A:B, 2, FALSE()) -> 75.7 | E20: =VLOOKUP(A20, Political!A:H, 8, FALSE()) -> 77.208333 | F20: =VLOOKUP(A20, Pollution!A:B, 2, FALSE()) -> 8.45 | G20: =VLOOKUP(A20, Climate!A:B, 2, FALSE()) -> 2389 | H20: =VLOOKUP(A20, English!A:C, 3, FALSE()) -> 608 | I20: =VLOOKUP(A20, Openness!A:C, 2, FALSE()) -> 31 | J20: =VLOOKUP(A20, Scenic!A:B, 2, FALSE()) -> 47 | K20: =VLOOKUP(A20, Disaster!A:H, 4, FALSE()) -> 1.79 | L20: =VLOOKUP(A20, LifeExp60!A:B, 2, FALSE()) -> 26.429
A21: Canada | B21: =VLOOKUP(A21, Sheet1!A:B, 2, FALSE()) -> 46.6 | C21: =VLOOKUP(A21, Safety!A:B, 2, FALSE()) -> 74.887989 | D21: =VLOOKUP(A21, Health!A:B, 2, FALSE()) -> 68.6 | E21: =VLOOKUP(A21, Political!A:H, 8, FALSE()) -> 82.791667 | F21: =VLOOKUP(A21, Pollution!A:B, 2, FALSE()) -> 6.55 | G21: =VLOOKUP(A21, Climate!A:B, 2, FALSE()) -> 2015 | H21: 700 | I21: =VLOOKUP(A21, Openness!A:C, 2, FALSE()) -> 39 | J21: =VLOOKUP(A21, Scenic!A:B, 2, FALSE()) -> 18 | K21: =VLOOKUP(A21, Disaster!A:H, 4, FALSE()) -> 26.08 | L21: =VLOOKUP(A21, LifeExp60!A:B, 2, FALSE()) -> 27.137
A22: Finland | B22: =VLOOKUP(A22, Sheet1!A:B, 2, FALSE()) -> 46.3 | C22: =VLOOKUP(A22, Safety!A:B, 2, FALSE()) -> 84.266946 | D22: =VLOOKUP(A22, Health!A:B, 2, FALSE()) -> 77.5 | E22: =VLOOKUP(A22, Political!A:H, 8, FALSE()) -> 88.296667 | F22: =VLOOKUP(A22, Pollution!A:B, 2, FALSE()) -> 4.57 | G22: =VLOOKUP(A22, Climate!A:B, 2, FALSE()) -> 1737 | H22: =VLOOKUP(A22, English!A:C, 3, FALSE()) -> 603 | I22: =VLOOKUP(A22, Openness!A:C, 2, FALSE()) -> 50 | J22: =VLOOKUP(A22, Scenic!A:B, 2, FALSE()) -> 17 | K22: =VLOOKUP(A22, Disaster!A:H, 4, FALSE()) -> 0.51 | L22: =VLOOKUP(A22, LifeExp60!A:B, 2, FALSE()) -> 26.546
A23: United Arab Emirates | B23: =VLOOKUP(A23, Sheet1!A:B, 2, FALSE()) -> 46.8 | C23: =VLOOKUP(A23, Safety!A:B, 2, FALSE()) -> 87.891524 | D23: =VLOOKUP(A23, Health!A:B, 2, FALSE()) -> 70.8 | E23: =VLOOKUP(A23, Political!A:H, 8, FALSE()) -> 68.031667 | F23: =VLOOKUP(A23, Pollution!A:B, 2, FALSE()) -> 57.19 | G23: =VLOOKUP(A23, Climate!A:B, 2, FALSE()) -> 1720 | H23: =VLOOKUP(A23, English!A:C, 3, FALSE()) -> 487 | I23: =VLOOKUP(A23, Openness!A:C, 2, FALSE()) -> 16 | J23: =VLOOKUP(A23, Scenic!A:B, 2, FALSE()) -> 60 | K23: =VLOOKUP(A23, Disaster!A:H, 4, FALSE()) -> 4.72 | L23: =VLOOKUP(A23, LifeExp60!A:B, 2, FALSE()) -> 25.574
A24: France | B24: =VLOOKUP(A24, Sheet1!A:B, 2, FALSE()) -> 45.7 | C24: =VLOOKUP(A24, Safety!A:B, 2, FALSE()) -> 80.369769 | D24: =VLOOKUP(A24, Health!A:B, 2, FALSE()) -> 76.9 | E24: =VLOOKUP(A24, Political!A:H, 8, FALSE()) -> 73.39 | F24: =VLOOKUP(A24, Pollution!A:B, 2, FALSE()) -> 8.23 | G24: =VLOOKUP(A24, Climate!A:B, 2, FALSE()) -> 2710 | H24: =VLOOKUP(A24, English!A:C, 3, FALSE()) -> 539 | I24: =VLOOKUP(A24, Openness!A:C, 2, FALSE()) -> 34 | J24: =VLOOKUP(A24, Scenic!A:B, 2, FALSE()) -> 20 | K24: =VLOOKUP(A24, Disaster!A:H, 4, FALSE()) -> 2.63 | L24: =VLOOKUP(A24, LifeExp60!A:B, 2, FALSE()) -> 28.253
A25: New Zealand | B25: =VLOOKUP(A25, Sheet1!A:B, 2, FALSE()) -> 43.9 | C25: =VLOOKUP(A25, Safety!A:B, 2, FALSE()) -> 79.288776 | D25: =VLOOKUP(A25, Health!A:B, 2, FALSE()) -> 68.1 | E25: =VLOOKUP(A25, Political!A:H, 8, FALSE()) -> 87.281667 | F25: =VLOOKUP(A25, Pollution!A:B, 2, FALSE()) -> 6.88 | G25: =VLOOKUP(A25, Climate!A:B, 2, FALSE()) -> 3149 | H25: 700 | I25: =VLOOKUP(A25, Openness!A:C, 2, FALSE()) -> 21 | J25: =VLOOKUP(A25, Scenic!A:B, 2, FALSE()) -> 2 | K25: =VLOOKUP(A25, Disaster!A:H, 4, FALSE()) -> 18.1 | L25: =VLOOKUP(A25, LifeExp60!A:B, 2, FALSE()) -> 26.177
A26: Puerto Rico | B26: =VLOOKUP(A26, Sheet1!A:B, 2, FALSE()) -> 45.8 | C26: =VLOOKUP(A26, Safety!A:B, 2, FALSE()) -> 36.118545 | D26: =VLOOKUP(A26, Health!A:B, 2, FALSE()) -> 58.7 | E26: =VLOOKUP(A26, Political!A:H, 8, FALSE()) -> 61.305 | F26: =VLOOKUP(A26, Pollution!A:B, 2, FALSE()) -> 7.84 | G26: =VLOOKUP(A26, Climate!A:B, 2, FALSE()) -> #N/A | H26: 700 | I26: =VLOOKUP(A26, Openness!A:C, 2, FALSE()) -> #N/A | J26: =VLOOKUP(A26, Scenic!A:B, 2, FALSE()) -> #N/A | K26: =VLOOKUP(A26, Disaster!A:H, 4, FALSE()) -> #N/A | L26: =VLOOKUP(A26, LifeExp60!A:B, 2, FALSE()) -> 27.581
A27: Oman | B27: =VLOOKUP(A27, Sheet1!A:B, 2, FALSE()) -> 30.2 | C27: =VLOOKUP(A27, Safety!A:B, 2, FALSE()) -> 97.006799 | D27: =VLOOKUP(A27, Health!A:B, 2, FALSE()) -> 62.7 | E27: =VLOOKUP(A27, Political!A:H, 8, FALSE()) -> 61.008333 | F27: =VLOOKUP(A27, Pollution!A:B, 2, FALSE()) -> 46.86 | G27: =VLOOKUP(A27, Climate!A:B, 2, FALSE()) -> 1762 | H27: =VLOOKUP(A27, English!A:C, 3, FALSE()) -> 407 | I27: =VLOOKUP(A27, Openness!A:C, 2, FALSE()) -> 12 | J27: =VLOOKUP(A27, Scenic!A:B, 2, FALSE()) -> 79 | K27: =VLOOKUP(A27, Disaster!A:H, 4, FALSE()) -> 7.04 | L27: =VLOOKUP(A27, LifeExp60!A:B, 2, FALSE()) -> 24.615
A28: South Korea | B28: =VLOOKUP(A28, Sheet1!A:B, 2, FALSE()) -> 37 | C28: =VLOOKUP(A28, Safety!A:B, 2, FALSE()) -> 91.030496 | D28: =VLOOKUP(A28, Health!A:B, 2, FALSE()) -> 83 | E28: =VLOOKUP(A28, Political!A:H, 8, FALSE()) -> 76.058333 | F28: =VLOOKUP(A28, Pollution!A:B, 2, FALSE()) -> 21.89 | G28: =VLOOKUP(A28, Climate!A:B, 2, FALSE()) -> 1890 | H28: =VLOOKUP(A28, English!A:C, 3, FALSE()) -> 522 | I28: =VLOOKUP(A28, Openness!A:C, 2, FALSE()) -> 36 | J28: =VLOOKUP(A28, Scenic!A:B, 2, FALSE()) -> 70 | K28: =VLOOKUP(A28, Disaster!A:H, 4, FALSE()) -> 9.83 | L28: =VLOOKUP(A28, LifeExp60!A:B, 2, FALSE()) -> 28.35
A29: Bahrain | B29: =VLOOKUP(A29, Sheet1!A:B, 2, FALSE()) -> 35.1 | C29: =VLOOKUP(A29, Safety!A:B, 2, FALSE()) -> 95.883764 | D29: =VLOOKUP(A29, Health!A:B, 2, FALSE()) -> #N/A | E29: =VLOOKUP(A29, Political!A:H, 8, FALSE()) -> 56.581667 | F29: =VLOOKUP(A29, Pollution!A:B, 2, FALSE()) -> 56.57 | G29: =VLOOKUP(A29, Climate!A:B, 2, FALSE()) -> #N/A | H29: =VLOOKUP(A29, English!A:C, 3, FALSE()) -> #N/A | I29: =VLOOKUP(A29, Openness!A:C, 2, FALSE()) -> 18 | J29: =VLOOKUP(A29, Scenic!A:B, 2, FALSE()) -> 84 | K29: =VLOOKUP(A29, Disaster!A:H, 4, FALSE()) -> 0.12 | L29: =VLOOKUP(A29, LifeExp60!A:B, 2, FALSE()) -> 24.508
A30: Japan | B30: =VLOOKUP(A30, Sheet1!A:B, 2, FALSE()) -> 32.1 | C30: =VLOOKUP(A30, Safety!A:B, 2, FALSE()) -> 95.257801 | D30: =VLOOKUP(A30, Health!A:B, 2, FALSE()) -> 79.9 | E30: =VLOOKUP(A30, Political!A:H, 8, FALSE()) -> 82.961667 | F30: =VLOOKUP(A30, Pollution!A:B, 2, FALSE()) -> 11.45 | G30: =VLOOKUP(A30, Climate!A:B, 2, FALSE()) -> 2190 | H30: =VLOOKUP(A30, English!A:C, 3, FALSE()) -> 446 | I30: =VLOOKUP(A30, Openness!A:C, 2, FALSE()) -> 35 | J30: =VLOOKUP(A30, Scenic!A:B, 2, FALSE()) -> 23 | K30: =VLOOKUP(A30, Disaster!A:H, 4, FALSE()) -> 43.35 | L30: =VLOOKUP(A30, LifeExp60!A:B, 2, FALSE()) -> 29.482
A31: Spain | B31: =VLOOKUP(A31, Sheet1!A:B, 2, FALSE()) -> 38.1 | C31: =VLOOKUP(A31, Safety!A:B, 2, FALSE()) -> 87.918709 | D31: =VLOOKUP(A31, Health!A:B, 2, FALSE()) -> 76.7 | E31: =VLOOKUP(A31, Political!A:H, 8, FALSE()) -> 69.885 | F31: =VLOOKUP(A31, Pollution!A:B, 2, FALSE()) -> 10.08 | G31: =VLOOKUP(A31, Climate!A:B, 2, FALSE()) -> 3001 | H31: =VLOOKUP(A31, English!A:C, 3, FALSE()) -> 540 | I31: =VLOOKUP(A31, Openness!A:C, 2, FALSE()) -> 11 | J31: =VLOOKUP(A31, Scenic!A:B, 2, FALSE()) -> 5 | K31: =VLOOKUP(A31, Disaster!A:H, 4, FALSE()) -> 7.54 | L31: =VLOOKUP(A31, LifeExp60!A:B, 2, FALSE()) -> 27.982
A32: Estonia | B32: =VLOOKUP(A32, Sheet1!A:B, 2, FALSE()) -> 39.2 | C32: =VLOOKUP(A32, Safety!A:B, 2, FALSE()) -> 78.598371 | D32: =VLOOKUP(A32, Health!A:B, 2, FALSE()) -> 75.4 | E32: =VLOOKUP(A32, Political!A:H, 8, FALSE()) -> 81.496667 | F32: =VLOOKUP(A32, Pollution!A:B, 2, FALSE()) -> 5.92 | G32: =VLOOKUP(A32, Climate!A:B, 2, FALSE()) -> 1908 | H32: =VLOOKUP(A32, English!A:C, 3, FALSE()) -> 561 | I32: =VLOOKUP(A32, Openness!A:C, 2, FALSE()) -> #N/A | J32: =VLOOKUP(A32, Scenic!A:B, 2, FALSE()) -> 62 | K32: =VLOOKUP(A32, Disaster!A:H, 4, FALSE()) -> 0.53 | L32: =VLOOKUP(A32, LifeExp60!A:B, 2, FALSE()) -> 25.402
A33: Italy | B33: =VLOOKUP(A33, Sheet1!A:B, 2, FALSE()) -> 41.9 | C33: =VLOOKUP(A33, Safety!A:B, 2, FALSE()) -> 89.655495 | D33: =VLOOKUP(A33, Health!A:B, 2, FALSE()) -> 64.8 | E33: =VLOOKUP(A33, Political!A:H, 8, FALSE()) -> 69.39 | F33: =VLOOKUP(A33, Pollution!A:B, 2, FALSE()) -> 14.29 | G33: =VLOOKUP(A33, Climate!A:B, 2, FALSE()) -> 2758 | H33: =VLOOKUP(A33, English!A:C, 3, FALSE()) -> 513 | I33: =VLOOKUP(A33, Openness!A:C, 2, FALSE()) -> 33 | J33: =VLOOKUP(A33, Scenic!A:B, 2, FALSE()) -> 3 | K33: =VLOOKUP(A33, Disaster!A:H, 4, FALSE()) -> 8.86 | L33: =VLOOKUP(A33, LifeExp60!A:B, 2, FALSE()) -> 27.372
A34: Saudi Arabia | B34: =VLOOKUP(A34, Sheet1!A:B, 2, FALSE()) -> 30.3 | C34: =VLOOKUP(A34, Safety!A:B, 2, FALSE()) -> 84.818876 | D34: =VLOOKUP(A34, Health!A:B, 2, FALSE()) -> 62.2 | E34: =VLOOKUP(A34, Political!A:H, 8, FALSE()) -> 58.971667 | F34: =VLOOKUP(A34, Pollution!A:B, 2, FALSE()) -> 73.52 | G34: =VLOOKUP(A34, Climate!A:B, 2, FALSE()) -> 1986 | H34: =VLOOKUP(A34, English!A:C, 3, FALSE()) -> 404 | I34: =VLOOKUP(A34, Openness!A:C, 2, FALSE()) -> 25 | J34: =VLOOKUP(A34, Scenic!A:B, 2, FALSE()) -> 83 | K34: =VLOOKUP(A34, Disaster!A:H, 4, FALSE()) -> 4.32 | L34: =VLOOKUP(A34, LifeExp60!A:B, 2, FALSE()) -> 23.887
A35: Cyprus | B35: =VLOOKUP(A35, Sheet1!A:B, 2, FALSE()) -> 42.4 | C35: =VLOOKUP(A35, Safety!A:B, 2, FALSE()) -> 84.558876 | D35: =VLOOKUP(A35, Health!A:B, 2, FALSE()) -> 56.6 | E35: =VLOOKUP(A35, Political!A:H, 8, FALSE()) -> 69.46 | F35: =VLOOKUP(A35, Pollution!A:B, 2, FALSE()) -> 16.07 | G35: =VLOOKUP(A35, Climate!A:B, 2, FALSE()) -> 2823 | H35: =VLOOKUP(A35, English!A:C, 3, FALSE()) -> 537 | I35: =VLOOKUP(A35, Openness!A:C, 2, FALSE()) -> 17 | J35: =VLOOKUP(A35, Scenic!A:B, 2, FALSE()) -> 35 | K35: =VLOOKUP(A35, Disaster!A:H, 4, FALSE()) -> 0.68 | L35: =VLOOKUP(A35, LifeExp60!A:B, 2, FALSE()) -> 25.234
A36: Malta | B36: =VLOOKUP(A36, Sheet1!A:B, 2, FALSE()) -> 43.3 | C36: =VLOOKUP(A36, Safety!A:B, 2, FALSE()) -> 89.728948 | D36: =VLOOKUP(A36, Health!A:B, 2, FALSE()) -> 53.3 | E36: =VLOOKUP(A36, Political!A:H, 8, FALSE()) -> 68.53 | F36: =VLOOKUP(A36, Pollution!A:B, 2, FALSE()) -> 10.81 | G36: =VLOOKUP(A36, Climate!A:B, 2, FALSE()) -> #N/A | H36: =VLOOKUP(A36, English!A:C, 3, FALSE()) -> #N/A | I36: =VLOOKUP(A36, Openness!A:C, 2, FALSE()) -> 32 | J36: =VLOOKUP(A36, Scenic!A:B, 2, FALSE()) -> #N/A | K36: =VLOOKUP(A36, Disaster!A:H, 4, FALSE()) -> 0.15 | L36: =VLOOKUP(A36, LifeExp60!A:B, 2, FALSE()) -> 27.533
A37: Czech Republic | B37: =VLOOKUP(A37, Sheet1!A:B, 2, FALSE()) -> 37 | C37: =VLOOKUP(A37, Safety!A:B, 2, FALSE()) -> 86.894635 | D37: =VLOOKUP(A37, Health!A:B, 2, FALSE()) -> 75.6 | E37: =VLOOKUP(A37, Political!A:H, 8, FALSE()) -> 76.043333 | F37: =VLOOKUP(A37, Pollution!A:B, 2, FALSE()) -> 12.75 | G37: =VLOOKUP(A37, Climate!A:B, 2, FALSE()) -> 2342 | H37: =VLOOKUP(A37, English!A:C, 3, FALSE()) -> 582 | I37: =VLOOKUP(A37, Openness!A:C, 2, FALSE()) -> 47 | J37: =VLOOKUP(A37, Scenic!A:B, 2, FALSE()) -> 53 | K37: =VLOOKUP(A37, Disaster!A:H, 4, FALSE()) -> 0.1 | L37: =VLOOKUP(A37, LifeExp60!A:B, 2, FALSE()) -> 24.623
A38: Taiwan | B38: =VLOOKUP(A38, Sheet1!A:B, 2, FALSE()) -> 32.6 | C38: =VLOOKUP(A38, Safety!A:B, 2, FALSE()) -> #N/A | D38: =VLOOKUP(A38, Health!A:B, 2, FALSE()) -> 87.1 | E38: =VLOOKUP(A38, Political!A:H, 8, FALSE()) -> 78.288333 | F38: =VLOOKUP(A38, Pollution!A:B, 2, FALSE()) -> #N/A | G38: =VLOOKUP(A38, Climate!A:B, 2, FALSE()) -> 2218 | H38: =VLOOKUP(A38, English!A:C, 3, FALSE()) -> #N/A | I38: =VLOOKUP(A38, Openness!A:C, 2, FALSE()) -> #N/A | J38: =VLOOKUP(A38, Scenic!A:B, 2, FALSE()) -> #N/A | K38: =VLOOKUP(A38, Disaster!A:H, 4, FALSE()) -> #N/A | L38: =VLOOKUP(A38, LifeExp60!A:B, 2, FALSE()) -> #N/A
... A153: Libya | B153: =VLOOKUP(A153, Sheet1!A:B, 2, FALSE()) -> 12.7 | C153: =VLOOKUP(A153, Safety!A:B, 2, FALSE()) -> #N/A | D153: =VLOOKUP(A153, Health!A:B, 2, FALSE()) -> #N/A | E153: =VLOOKUP(A153, Political!A:H, 8, FALSE()) -> 27.013333 | F153: =VLOOKUP(A153, Pollution!A:B, 2, FALSE()) -> 20.01 | G153: =VLOOKUP(A153, Climate!A:B, 2, FALSE()) -> #N/A | H153: =VLOOKUP(A153, English!A:C, 3, FALSE()) -> 395 | I153: =VLOOKUP(A153, Openness!A:C, 2, FALSE()) -> #N/A | J153: =VLOOKUP(A153, Scenic!A:B, 2, FALSE()) -> #N/A | K153: =VLOOKUP(A153, Disaster!A:H, 4, FALSE()) -> 4.75 | L153: =VLOOKUP(A153, LifeExp60!A:B, 2, FALSE()) -> 18.553

Sheet Safety
A1: Country | B1: Safety_homicide_score | C1: Homicide_rate_per_100k | D1: Year | E1: Active (tab 1 uses col B). Source: UNODC via Our World in Data (homicide-rate-unodc), latest year per country, downloaded Oct 2026. Score = 100*(1-LN(1+rate)/LN(1+max rate)): 100 = no homicides, higher = safer; log scale because rates are very skewed (median ~2.6, max ~76). Years older than 2015 flagged. | G1: Country | H1: Safety_2026MY | J1: Country | K1: Safety index_2025 | L1: Numbeo. Active: 2026 Mid-Year (A:B). | M1: Numbeo perceived safety (2026 Mid-Year and 2025) - kept for reference, no longer used.
A2: American Samoa | B2: =100*(1-LN(1+C2)/LN(1+MAX($C$2:$C$209))) -> 100 | C2: 0 | D2: 2019 | G2: Andorra | H2: 86.5 | J2: Andorra | K2: 84.7
A3: Gibraltar | B3: =100*(1-LN(1+C3)/LN(1+MAX($C$2:$C$209))) -> 100 | C3: 0 | D3: 2024 | G3: United Arab Emirates | H3: 86.4 | J3: United Arab Emirates | K3: 84.5
A4: Isle Of Man | B4: =100*(1-LN(1+C4)/LN(1+MAX($C$2:$C$209))) -> 100 | C4: 0 | D4: 2016 | G4: Qatar | H4: 84.8 | J4: Qatar | K4: 84.2
A5: Monaco | B5: =100*(1-LN(1+C5)/LN(1+MAX($C$2:$C$209))) -> 100 | C5: 0 | D5: 2008 | E5: old data (latest year < 2015) | G5: Taiwan | H5: 82.9 | J5: Taiwan | K5: 82.9
A6: Montserrat | B6: =100*(1-LN(1+C6)/LN(1+MAX($C$2:$C$209))) -> 100 | C6: 0 | D6: 2018 | G6: Macao (China) | H6: 81.8 | J6: Oman | K6: 81.7
A7: Saint Helena | B7: =100*(1-LN(1+C7)/LN(1+MAX($C$2:$C$209))) -> 100 | C7: 0 | D7: 2009 | E7: old data (latest year < 2015) | G7: Oman | H7: 81.7 | J7: Isle Of Man | K7: 79
A8: San Marino | B8: =100*(1-LN(1+C8)/LN(1+MAX($C$2:$C$209))) -> 100 | C8: 0 | D8: 2011 | E8: old data (latest year < 2015) | G8: Isle Of Man | H8: 80.3 | J8: Hong Kong (China) | K8: 78.5
A9: Tuvalu | B9: =100*(1-LN(1+C9)/LN(1+MAX($C$2:$C$209))) -> 100 | C9: 0 | D9: 2019 | G9: Hong Kong (China) | H9: 78.2 | J9: Armenia | K9: 77.9
A10: Vatican | B10: =100*(1-LN(1+C10)/LN(1+MAX($C$2:$C$209))) -> 100 | C10: 0 | D10: 2023 | G10: Armenia | H10: 78 | J10: Singapore | K10: 77.4
A11: Jersey | B11: =100*(1-LN(1+C11)/LN(1+MAX($C$2:$C$209))) -> 100 | C11: 0 | D11: 2010 | E11: Channel Islands figure (2010) | G11: Japan | H11: 77.8 | J11: Japan | K11: 77.1
A12: Guernsey | B12: =100*(1-LN(1+C12)/LN(1+MAX($C$2:$C$209))) -> 100 | C12: 0 | D12: 2010 | E12: Channel Islands figure (2010) | G12: Bahrain | H12: 77.7 | J12: Monaco | K12: 76.7
A13: Singapore | B13: =100*(1-LN(1+C13)/LN(1+MAX($C$2:$C$209))) -> 98.465492 | C13: 0.069 | D13: 2023 | G13: Singapore | H13: 77.7 | J13: Estonia | K13: 76.3
A14: Qatar | B14: =100*(1-LN(1+C14)/LN(1+MAX($C$2:$C$209))) -> 98.465492 | C14: 0.069 | D14: 2022 | G14: China | H14: 77 | J14: Slovenia | K14: 76.2
A15: Oman | B15: =100*(1-LN(1+C15)/LN(1+MAX($C$2:$C$209))) -> 97.006799 | C15: 0.139 | D15: 2023 | G15: Saudi Arabia | H15: 76.8 | J15: Saudi Arabia | K15: 76.1
A16: Bahrain | B16: =100*(1-LN(1+C16)/LN(1+MAX($C$2:$C$209))) -> 95.883764 | C16: 0.196 | D16: 2022 | G16: Estonia | H16: 76.5 | J16: China | K16: 76
A17: Japan | B17: =100*(1-LN(1+C17)/LN(1+MAX($C$2:$C$209))) -> 95.257801 | C17: 0.229 | D17: 2023 | G17: Slovenia | H17: 75.5 | J17: Bahrain | K17: 75.5
A18: Kuwait | B18: =100*(1-LN(1+C18)/LN(1+MAX($C$2:$C$209))) -> 94.868153 | C18: 0.25 | D18: 2020 | G18: Croatia | H18: 74.8 | J18: South Korea | K18: 75.1
A19: Indonesia | B19: =100*(1-LN(1+C19)/LN(1+MAX($C$2:$C$209))) -> 93.895502 | C19: 0.304 | D19: 2022 | G19: Iceland | H19: 74.5 | J19: Croatia | K19: 74.5
A20: Vanuatu | B20: =100*(1-LN(1+C20)/LN(1+MAX($C$2:$C$209))) -> 93.355169 | C20: 0.335 | D20: 2020 | G20: Monaco | H20: 74.5 | J20: Iceland | K20: 74.3
A21: French Polynesia | B21: =100*(1-LN(1+C21)/LN(1+MAX($C$2:$C$209))) -> 92.743214 | C21: 0.371 | D21: 2009 | E21: old data (latest year < 2015) | G21: Finland | H21: 73.7 | J21: Denmark | K21: 74
A22: Hong Kong (China) | B22: =100*(1-LN(1+C22)/LN(1+MAX($C$2:$C$209))) -> 92.659493 | C22: 0.376 | D22: 2023 | G22: Rwanda | H22: 73.6 | J22: Georgia | K22: 73.7
A23: South Korea | B23: =100*(1-LN(1+C23)/LN(1+MAX($C$2:$C$209))) -> 91.030496 | C23: 0.477 | D23: 2023 | G23: Czech Republic | H23: 73.3 | J23: Czech Republic | K23: 73.5
A24: Brunei | B24: =100*(1-LN(1+C24)/LN(1+MAX($C$2:$C$209))) -> 90.890784 | C24: 0.486 | D24: 2013 | E24: old data (latest year < 2015) | G24: Denmark | H24: 73.2 | J24: Switzerland | K24: 73.5
A25: China | B25: =100*(1-LN(1+C25)/LN(1+MAX($C$2:$C$209))) -> 90.644485 | C25: 0.502 | D25: 2020 | G25: Georgia | H25: 73.1 | J25: Finland | K25: 73.2
A26: Macao (China) | B26: =100*(1-LN(1+C26)/LN(1+MAX($C$2:$C$209))) -> 89.773132 | C26: 0.56 | D26: 2023 | G26: Uzbekistan | H26: 72.7 | J26: Rwanda | K26: 73.1
A27: Malta | B27: =100*(1-LN(1+C27)/LN(1+MAX($C$2:$C$209))) -> 89.728948 | C27: 0.563 | D27: 2023 | G27: Netherlands | H27: 72.3 | J27: Netherlands | K27: 73.1
A28: Slovenia | B28: =100*(1-LN(1+C28)/LN(1+MAX($C$2:$C$209))) -> 89.684848 | C28: 0.566 | D28: 2023 | G28: Switzerland | H28: 71.9 | J28: Uzbekistan | K28: 72.1
A29: Italy | B29: =100*(1-LN(1+C29)/LN(1+MAX($C$2:$C$209))) -> 89.655495 | C29: 0.568 | D29: 2023 | G29: Poland | H29: 71.3 | J29: Poland | K29: 71
A30: Switzerland | B30: =100*(1-LN(1+C30)/LN(1+MAX($C$2:$C$209))) -> 89.234036 | C30: 0.597 | D30: 2023 | G30: Cayman Islands | H30: 71 | J30: Brunei | K30: 70.7
A31: Maldives | B31: =100*(1-LN(1+C31)/LN(1+MAX($C$2:$C$209))) -> 88.976273 | C31: 0.615 | D31: 2019 | G31: Austria | H31: 70.8 | J31: Austria | K31: 70.5
A32: Palestine | B32: =100*(1-LN(1+C32)/LN(1+MAX($C$2:$C$209))) -> 88.876806 | C32: 0.622 | D32: 2022 | G32: South Korea | H32: 70.3 | J32: Cayman Islands | K32: 69.2
A33: Ireland | B33: =100*(1-LN(1+C33)/LN(1+MAX($C$2:$C$209))) -> 88.427504 | C33: 0.654 | D33: 2023 | G33: Brunei | H33: 70.1 | J33: Slovakia | K33: 69
A34: Croatia | B34: =100*(1-LN(1+C34)/LN(1+MAX($C$2:$C$209))) -> 88.247452 | C34: 0.667 | D34: 2023 | G34: Slovakia | H34: 69.1 | J34: Azerbaijan | K34: 68.2
A35: Spain | B35: =100*(1-LN(1+C35)/LN(1+MAX($C$2:$C$209))) -> 87.918709 | C35: 0.691 | D35: 2023 | G35: Azerbaijan | H35: 68.5 | J35: Israel | K35: 68.2
A36: Netherlands | B36: =100*(1-LN(1+C36)/LN(1+MAX($C$2:$C$209))) -> 87.918709 | C36: 0.691 | D36: 2023 | G36: Israel | H36: 68.2 | J36: Portugal | K36: 67.9
... A75: Luxembourg | B75: =100*(1-LN(1+C75)/LN(1+MAX($C$2:$C$209))) -> 78.643759 | C75: 1.531 | D75: 2022 | G75: Kazakhstan | H75: 54.8 | J75: Zambia | K75: 54.4
A76: Vietnam | B76: =100*(1-LN(1+C76)/LN(1+MAX($C$2:$C$209))) -> 78.607442 | C76: 1.535 | D76: 2011 | E76: old data (latest year < 2015) | G76: Canada | H76: 54.4 | J76: Canada | K76: 54.3
A77: Estonia | B77: =100*(1-LN(1+C77)/LN(1+MAX($C$2:$C$209))) -> 78.598371 | C77: 1.536 | D77: 2023 | G77: Sudan | H77: 54.4 | J77: Indonesia | K77: 54
A78: Israel | B78: =100*(1-LN(1+C78)/LN(1+MAX($C$2:$C$209))) -> 77.796346 | C78: 1.626 | D78: 2022 | G78: Egypt | H78: 54 | J78: Greece | K78: 53.6
A79: Morocco | B79: =100*(1-LN(1+C79)/LN(1+MAX($C$2:$C$209))) -> 77.440051 | C79: 1.667 | D79: 2024 | G79: Greece | H79: 54 | J79: Lebanon | K79: 53.2
A80: Albania | B80: =100*(1-LN(1+C80)/LN(1+MAX($C$2:$C$209))) -> 76.693464 | C80: 1.755 | D80: 2024 | G80: Indonesia | H80: 53.8 | J80: Italy | K80: 53.1
A81: Malawi | B81: =100*(1-LN(1+C81)/LN(1+MAX($C$2:$C$209))) -> 76.518826 | C81: 1.776 | D81: 2012 | E81: old data (latest year < 2015) | G81: Lebanon | H81: 53.2 | J81: Ukraine | K81: 53
A82: Reunion | B82: =100*(1-LN(1+C82)/LN(1+MAX($C$2:$C$209))) -> 76.411378 | C82: 1.789 | D82: 2009 | E82: old data (latest year < 2015) | G82: Ukraine | H82: 53.1 | J82: Egypt | K82: 52.7
A83: Cambodia | B83: =100*(1-LN(1+C83)/LN(1+MAX($C$2:$C$209))) -> 76.157164 | C83: 1.82 | D83: 2011 | E83: old data (latest year < 2015) | G83: Zambia | H83: 52.9 | J83: Australia | K83: 52.7
A84: Ghana | B84: =100*(1-LN(1+C84)/LN(1+MAX($C$2:$C$209))) -> 76.06763 | C84: 1.831 | D84: 2022 | G84: Morocco | H84: 52.9 | J84: Ireland | K84: 52.4
A85: Kosovo (Disputed Territory) | B85: =100*(1-LN(1+C85)/LN(1+MAX($C$2:$C$209))) -> 75.553508 | C85: 1.895 | D85: 2021 | G85: Australia | H85: 52.6 | J85: Morocco | K85: 52.2
A86: Aruba | B86: =100*(1-LN(1+C86)/LN(1+MAX($C$2:$C$209))) -> 75.237922 | C86: 1.935 | D86: 2014 | E86: old data (latest year < 2015) | G86: Italy | H86: 52.6 | J86: Sweden | K86: 52
A87: Asia (UN) | B87: =100*(1-LN(1+C87)/LN(1+MAX($C$2:$C$209))) -> 74.911153 | C87: 1.977 | D87: 2024 | G87: Belarus | H87: 52.2 | J87: New Zealand | K87: 51.8
A88: Canada | B88: =100*(1-LN(1+C88)/LN(1+MAX($C$2:$C$209))) -> 74.887989 | C88: 1.98 | D88: 2023 | G88: Sweden | H88: 52.2 | J88: United Kingdom | K88: 51.7
A89: Azerbaijan | B89: =100*(1-LN(1+C89)/LN(1+MAX($C$2:$C$209))) -> 74.78788 | C89: 1.993 | D89: 2024 | G89: Malaysia | H89: 52 | J89: Malaysia | K89: 51.1
A90: Georgia | B90: =100*(1-LN(1+C90)/LN(1+MAX($C$2:$C$209))) -> 74.520504 | C90: 2.028 | D90: 2019 | G90: United Kingdom | H90: 51.8 | J90: United States | K90: 50.8
A91: Fiji | B91: =100*(1-LN(1+C91)/LN(1+MAX($C$2:$C$209))) -> 74.308818 | C91: 2.056 | D91: 2023 | G91: New Zealand | H91: 51.2 | J91: Belgium | K91: 50.6
A92: Syria | B92: =100*(1-LN(1+C92)/LN(1+MAX($C$2:$C$209))) -> 74.286253 | C92: 2.059 | D92: 2010 | E92: old data (latest year < 2015) | G92: Cambodia | H92: 51.2 | J92: Belarus | K92: 50.2
A93: Nepal | B93: =100*(1-LN(1+C93)/LN(1+MAX($C$2:$C$209))) -> 73.758566 | C93: 2.13 | D93: 2020 | G93: Ireland | H93: 50.9 | J93: Mauritius | K93: 50
A94: Armenia | B94: =100*(1-LN(1+C94)/LN(1+MAX($C$2:$C$209))) -> 73.192478 | C94: 2.208 | D94: 2023 | G94: United States | H94: 50.8 | J94: Iran | K94: 49.5
A95: Sierra Leone | B95: =100*(1-LN(1+C95)/LN(1+MAX($C$2:$C$209))) -> 73.07806 | C95: 2.224 | D95: 2020 | G95: Mauritius | H95: 50.7 | J95: Ethiopia | K95: 49.3
A96: Lebanon | B96: =100*(1-LN(1+C96)/LN(1+MAX($C$2:$C$209))) -> 72.928745 | C96: 2.245 | D96: 2020 | G96: Belgium | H96: 50.5 | J96: Nicaragua | K96: 49.2
A97: Mauritius | B97: =100*(1-LN(1+C97)/LN(1+MAX($C$2:$C$209))) -> 72.738183 | C97: 2.272 | D97: 2022 | G97: Kyrgyzstan | H97: 50.5 | J97: Myanmar | K97: 49.1
A98: Bangladesh | B98: =100*(1-LN(1+C98)/LN(1+MAX($C$2:$C$209))) -> 72.251362 | C98: 2.342 | D98: 2018 | G98: Ethiopia | H98: 49.7 | J98: Cambodia | K98: 48.7
A99: Iran | B99: =100*(1-LN(1+C99)/LN(1+MAX($C$2:$C$209))) -> 72.025386 | C99: 2.375 | D99: 2014 | E99: old data (latest year < 2015) | G99: Iran | H99: 49.3 | J99: Uruguay | K99: 48
A100: Belarus | B100: =100*(1-LN(1+C100)/LN(1+MAX($C$2:$C$209))) -> 71.957345 | C100: 2.385 | D100: 2019 | G100: Nicaragua | H100: 49.2 | J100: Mongolia | K100: 47.9
A101: Europe (UN) | B101: =100*(1-LN(1+C101)/LN(1+MAX($C$2:$C$209))) -> 71.828618 | C101: 2.404 | D101: 2024 | G101: Botswana | H101: 48.9 | J101: Algeria | K101: 47.4
A102: Bhutan | B102: =100*(1-LN(1+C102)/LN(1+MAX($C$2:$C$209))) -> 71.400238 | C102: 2.468 | D102: 2020 | G102: Mongolia | H102: 48.8 | J102: Belize | K102: 47.3
A103: Latvia | B103: =100*(1-LN(1+C103)/LN(1+MAX($C$2:$C$209))) -> 71.208725 | C103: 2.497 | D103: 2023 | G103: Myanmar | H103: 48.5 | J103: Botswana | K103: 47.3
A104: Moldova | B104: =100*(1-LN(1+C104)/LN(1+MAX($C$2:$C$209))) -> 70.908179 | C104: 2.543 | D104: 2023 | G104: Belize | H104: 48.2 | J104: Mexico | K104: 46.6
A105: Kazakhstan | B105: =100*(1-LN(1+C105)/LN(1+MAX($C$2:$C$209))) -> 70.856309 | C105: 2.551 | D105: 2022 | G105: Maldives | H105: 47.6 | J105: Tanzania | K105: 46.5
A106: Myanmar | B106: =100*(1-LN(1+C106)/LN(1+MAX($C$2:$C$209))) -> 70.701397 | C106: 2.575 | D106: 2023 | G106: Uruguay | H106: 47.3 | J106: North Korea | K106: 45.9
A107: Andorra | B107: =100*(1-LN(1+C107)/LN(1+MAX($C$2:$C$209))) -> 70.637157 | C107: 2.585 | D107: 2020 | G107: Mexico | H107: 47.3 | J107: Maldives | K107: 45.9
A108: Lithuania | B108: =100*(1-LN(1+C108)/LN(1+MAX($C$2:$C$209))) -> 70.36295 | C108: 2.628 | D108: 2023 | G108: Algeria | H108: 47.2 | J108: Uganda | K108: 45.9
A109: Martinique | B109: =100*(1-LN(1+C109)/LN(1+MAX($C$2:$C$209))) -> 69.583918 | C109: 2.753 | D109: 2009 | E109: old data (latest year < 2015) | G109: Tanzania | H109: 46.5 | J109: Costa Rica | K109: 45.9
A110: India | B110: =100*(1-LN(1+C110)/LN(1+MAX($C$2:$C$209))) -> 69.207093 | C110: 2.815 | D110: 2022 | G110: Uganda | H110: 45.9 | J110: Kyrgyzstan | K110: 45.7
A111: Oceania (UN) | B111: =100*(1-LN(1+C111)/LN(1+MAX($C$2:$C$209))) -> 68.060631 | C111: 3.01 | D111: 2024 | G111: Costa Rica | H111: 45.8 | J111: France | K111: 44.6
A112: Liberia | B112: =100*(1-LN(1+C112)/LN(1+MAX($C$2:$C$209))) -> 67.623211 | C112: 3.087 | D112: 2012 | E112: old data (latest year < 2015) | G112: Kenya | H112: 44.8 | J112: Kenya | K112: 44
A113: New Caledonia | B113: =100*(1-LN(1+C113)/LN(1+MAX($C$2:$C$209))) -> 67.49415 | C113: 3.11 | D113: 2009 | E113: old data (latest year < 2015) | G113: El Salvador | H113: 44.5 | J113: Ivory Coast | K113: 43.6
A114: Turkey | B114: =100*(1-LN(1+C114)/LN(1+MAX($C$2:$C$209))) -> 66.843169 | C114: 3.228 | D114: 2023 | G114: Ivory Coast | H114: 44.3 | J114: Libya | K114: 43.6
A115: Sao Tome and Principe | B115: =100*(1-LN(1+C115)/LN(1+MAX($C$2:$C$209))) -> 66.821422 | C115: 3.232 | D115: 2011 | E115: old data (latest year < 2015) | G115: France | H115: 44.2 | J115: Fiji | K115: 43.4
A116: Sri Lanka | B116: =100*(1-LN(1+C116)/LN(1+MAX($C$2:$C$209))) -> 66.39607 | C116: 3.311 | D116: 2019 | G116: Libya | H116: 44.1 | J116: Bahamas | K116: 43.1
A117: Cook Islands | B117: =100*(1-LN(1+C117)/LN(1+MAX($C$2:$C$209))) -> 65.124854 | C117: 3.556 | D117: 2012 | E117: old data (latest year < 2015) | G117: Guatemala | H117: 43.8 | J117: Guatemala | K117: 42.3
A118: Mozambique | B118: =100*(1-LN(1+C118)/LN(1+MAX($C$2:$C$209))) -> 64.953864 | C118: 3.59 | D118: 2011 | E118: old data (latest year < 2015) | G118: Bahamas | H118: 43.4 | J118: El Salvador | K118: 41.4
A119: Rwanda | B119: =100*(1-LN(1+C119)/LN(1+MAX($C$2:$C$209))) -> 64.843898 | C119: 3.612 | D119: 2020 | G119: Fiji | H119: 42.9 | J119: Paraguay | K119: 40.2
A120: Solomon Islands | B120: =100*(1-LN(1+C120)/LN(1+MAX($C$2:$C$209))) -> 64.243446 | C120: 3.734 | D120: 2008 | E120: old data (latest year < 2015) | G120: Paraguay | H120: 41.7 | J120: Us Virgin Islands | K120: 40.1
A121: Tanzania | B121: =100*(1-LN(1+C121)/LN(1+MAX($C$2:$C$209))) -> 64.170691 | C121: 3.749 | D121: 2020 | G121: Us Virgin Islands | H121: 40.8 | J121: Mozambique | K121: 39.9
A122: Ukraine | B122: =100*(1-LN(1+C122)/LN(1+MAX($C$2:$C$209))) -> 64.035493 | C122: 3.777 | D122: 2021 | G122: Dominican Republic | H122: 40.4 | J122: Dominican Republic | K122: 39.5
A123: Afghanistan | B123: =100*(1-LN(1+C123)/LN(1+MAX($C$2:$C$209))) -> 62.839489 | C123: 4.032 | D123: 2021 | G123: Chile | H123: 39.4 | J123: Chile | K123: 39.5
A124: East Timor | B124: =100*(1-LN(1+C124)/LN(1+MAX($C$2:$C$209))) -> 62.68462 | C124: 4.066 | D124: 2015 | G124: Bangladesh | H124: 39.3 | J124: Zimbabwe | K124: 39.3
A125: Angola | B125: =100*(1-LN(1+C125)/LN(1+MAX($C$2:$C$209))) -> 62.539808 | C125: 4.098 | D125: 2016 | G125: Yemen | H125: 39.2 | J125: Colombia | K125: 39.1
A126: Marshall Islands | B126: =100*(1-LN(1+C126)/LN(1+MAX($C$2:$C$209))) -> 62.11962 | C126: 4.192 | D126: 1994 | E126: old data (latest year < 2015) | G126: Mozambique | H126: 39 | J126: Puerto Rico | K126: 38.5
A127: Guam | B127: =100*(1-LN(1+C127)/LN(1+MAX($C$2:$C$209))) -> 61.533597 | C127: 4.326 | D127: 2019 | G127: Zimbabwe | H127: 38.8 | J127: Bangladesh | K127: 38.4
A128: Pakistan | B128: =100*(1-LN(1+C128)/LN(1+MAX($C$2:$C$209))) -> 61.494767 | C128: 4.335 | D128: 2023 | G128: Puerto Rico | H128: 38.7 | J128: Ecuador | K128: 37.5
A129: Philippines | B129: =100*(1-LN(1+C129)/LN(1+MAX($C$2:$C$209))) -> 61.438795 | C129: 4.348 | D129: 2023 | G129: Colombia | H129: 38.7 | J129: Argentina | K129: 36.6
A130: Cayman Islands | B130: =100*(1-LN(1+C130)/LN(1+MAX($C$2:$C$209))) -> 61.35295 | C130: 4.368 | D130: 2020 | G130: Ecuador | H130: 38.3 | J130: Namibia | K130: 36.5
A131: Niger | B131: =100*(1-LN(1+C131)/LN(1+MAX($C$2:$C$209))) -> 61.139728 | C131: 4.418 | D131: 2012 | E131: old data (latest year < 2015) | G131: Somalia | H131: 37.9 | J131: Yemen | K131: 36.3
A132: Bolivia | B132: =100*(1-LN(1+C132)/LN(1+MAX($C$2:$C$209))) -> 61.139728 | C132: 4.418 | D132: 2023 | G132: Argentina | H132: 37 | J132: Somalia | K132: 36.1
A133: Cuba | B133: =100*(1-LN(1+C133)/LN(1+MAX($C$2:$C$209))) -> 60.949504 | C133: 4.463 | D133: 2019 | G133: Brazil | H133: 36.4 | J133: Brazil | K133: 35.5
A134: Argentina | B134: =100*(1-LN(1+C134)/LN(1+MAX($C$2:$C$209))) -> 60.823556 | C134: 4.493 | D134: 2023 | G134: Namibia | H134: 36.4 | J134: Bolivia | K134: 35
A135: Tunisia | B135: =100*(1-LN(1+C135)/LN(1+MAX($C$2:$C$209))) -> 60.001085 | C135: 4.693 | D135: 2020 | G135: Bolivia | H135: 35.8 | J135: Cameroon | K135: 34.5
A136: Northern America (UN) | B136: =100*(1-LN(1+C136)/LN(1+MAX($C$2:$C$209))) -> 59.616508 | C136: 4.789 | D136: 2024 | G136: Cameroon | H136: 35.2 | J136: Guyana | K136: 33.7
A137: Thailand | B137: =100*(1-LN(1+C137)/LN(1+MAX($C$2:$C$209))) -> 59.604593 | C137: 4.792 | D137: 2011 | E137: old data (latest year < 2015) | G137: Angola | H137: 34.6 | J137: Angola | K137: 33.7
A138: Kenya | B138: =100*(1-LN(1+C138)/LN(1+MAX($C$2:$C$209))) -> 59.289115 | C138: 4.872 | D138: 2022 | G138: Nigeria | H138: 33.4 | J138: Nigeria | K138: 33.4
...

Sheet Health
A1: Country | B1: Healthcare_2026MY | D1: Country | E1: Healthcare_2025 | F1: Numbeo. Active: 2026 Mid-Year (A:B).
A2: Taiwan | B2: 87.1 | D2: Taiwan | E2: 86.5
A3: South Korea | B3: 83 | D3: South Korea | E3: 82.8
A4: Japan | B4: 79.9 | D4: Japan | E4: 80
A5: Ecuador | B5: 78.2 | D5: Netherlands | E5: 79.3
A6: Netherlands | B6: 77.6 | D6: Denmark | E6: 78.4
A7: Thailand | B7: 77.6 | D7: Austria | E7: 77.9
A8: Austria | B8: 77.5 | D8: France | E8: 77.7
A9: Finland | B9: 77.5 | D9: Finland | E9: 77.5
A10: France | B10: 76.9 | D10: Thailand | E10: 77.5
A11: Spain | B11: 76.7 | D11: Spain | E11: 77.3
A12: Belgium | B12: 75.7 | D12: Ecuador | E12: 77.1
A13: Czech Republic | B13: 75.6 | D13: Belgium | E13: 75.9
... A98: Iraq | B98: 47.2 | D98: Venezuela | E98: 38.7
A99: Morocco | B99: 46.8
A100: Bangladesh | B100: 42.1
A101: Venezuela | B101: 39.4
A102: Syria | B102: 35.7

Sheet Political
A1: Country | B1: cc | C1: ge | D1: pv | E1: rl | F1: rq | G1: va | H1: Average | I1: Political stability_2025: World Bank WGI 2026 release, data year 2025, "Governance score (0-100)" averaged over 6 dimensions. NOTE: WB dropped percentile ranks; this scale is not directly comparable with the 2023 block. | K1: Country | L1: cc | M1: ge | N1: pv | O1: rl | P1: rq | Q1: va | R1: Average | S1: Political stability_2023 (percentile ranks). Korea rows corrected.
A2: Afghanistan | B2: 21.7 | C2: 12.03 | D2: 29.81 | E2: 28.13 | F2: 30.76 | G2: 17.66 | H2: =AVERAGE(B2:G2) -> 23.348333 | K2: Afghanistan | L2: 13.679245 | M2: 1.4150944 | N2: 1.421801 | O2: 5.1886792 | P2: 9.4339619 | Q2: 1.9607843 | R2: 5.5165943
A3: Albania | B3: 41.97 | C3: 61.98 | D3: 67.18 | E3: 57.99 | F3: 60.67 | G3: 60.04 | H3: =AVERAGE(B3:G3) -> 58.305 | K3: Albania | L3: 43.396225 | M3: 60.377357 | N3: 51.658768 | O3: 45.754719 | P3: 58.490566 | Q3: 53.92157 | R3: 52.266534
A4: Algeria | B4: 37.33 | C4: 48.39 | D4: 54 | E4: 47.88 | F4: 41.91 | G4: 37.81 | H4: =AVERAGE(B4:G4) -> 44.553333 | K4: Algeria | L4: 30.188679 | M4: 27.35849 | N4: 23.22275 | O4: 26.415094 | P4: 16.037735 | Q4: 22.058823 | R4: 24.213595
A5: American Samoa | B5: 71.84 | C5: 70.14 | D5: 90.14 | E5: 80.85 | F5: 61.94 | H5: =AVERAGE(B5:G5) -> 74.982 | K5: American Samoa | L5: 87.735847 | M5: 73.113205 | N5: 91.94313 | O5: 85.377357 | P5: 68.396225 | R5: 81.313153
A6: Andorra | B6: 71.84 | C6: 80.58 | D6: 93 | E6: 84.61 | F6: 70.13 | G6: 72.29 | H6: =AVERAGE(B6:G6) -> 78.741667 | K6: Andorra | L6: 87.735847 | M6: 91.037735 | N6: 98.578201 | O6: 91.509438 | P6: 89.622643 | Q6: 78.92157 | R6: 89.567572
A7: Angola | B7: 34.28 | C7: 37.84 | D7: 57.94 | E7: 40.1 | F7: 42.69 | G7: 39.36 | H7: =AVERAGE(B7:G7) -> 42.035 | K7: Angola | L7: 29.245283 | M7: 14.622642 | N7: 32.227489 | O7: 14.622642 | P7: 22.64151 | Q7: 27.941177 | R7: 23.550124
A8: Anguilla | B8: 71.84 | C8: 74.91 | D8: 90.36 | E8: 69.2 | F8: 70.13 | H8: =AVERAGE(B8:G8) -> 75.288 | K8: Anguilla | L8: 87.735847 | M8: 87.264153 | N8: 91.94313 | O8: 75 | P8: 79.245285 | R8: 84.237683
A9: Antigua and Barbuda | B9: 59.9 | C9: 61.36 | D9: 86.78 | E9: 68.01 | F9: 66.17 | G9: 67.81 | H9: =AVERAGE(B9:G9) -> 68.338333 | K9: Antigua and Barbuda | L9: 62.264153 | M9: 63.679245 | N9: 80.568718 | O9: 59.905659 | P9: 70.28302 | Q9: 70.098038 | R9: 67.799805
A10: Argentina | B10: 40.26 | C10: 57.99 | D10: 68.45 | E10: 56.94 | F10: 53.89 | G10: 65.94 | H10: =AVERAGE(B10:G10) -> 57.245 | K10: Argentina | L10: 41.981133 | M10: 36.320755 | N10: 41.706161 | O10: 37.735847 | P10: 35.377357 | Q10: 63.235294 | R10: 42.726091
A11: Armenia | B11: 50.31 | C11: 47.49 | D11: 58.04 | E11: 54.26 | F11: 59.24 | G11: 59.94 | H11: =AVERAGE(B11:G11) -> 54.88 | K11: Armenia | L11: 57.07547 | M11: 43.867924 | N11: 17.061611 | O11: 49.056602 | P11: 52.830189 | Q11: 50.490196 | R11: 45.063665
A12: Aruba | B12: 65.57 | C12: 70.86 | D12: 87.78 | E12: 78.83 | F12: 72.28 | G12: 78.16 | H12: =AVERAGE(B12:G12) -> 75.58 | K12: Aruba | L12: 75.471695 | M12: 78.301888 | N12: 97.630333 | O12: 87.264153 | P12: 80.188683 | Q12: 80.392159 | R12: 83.208151
A13: Australia | B13: 85.12 | C13: 88.19 | D13: 79.29 | E13: 82.67 | F13: 84.23 | G13: 83.75 | H13: =AVERAGE(B13:G13) -> 83.875 | K13: Australia | L13: 95.754715 | M13: 93.867928 | N13: 79.62085 | O13: 91.981133 | P13: 99.528305 | Q13: 96.07843 | R13: 92.805227
A14: Austria | B14: 74.3 | C14: 83.94 | D14: 74.92 | E14: 85.83 | F14: 73.87 | G14: 83.77 | H14: =AVERAGE(B14:G14) -> 79.438333 | K14: Austria | L14: 83.490562 | M14: 89.622643 | N14: 71.56398 | O14: 97.169815 | P14: 90.094337 | Q14: 93.627449 | R14: 87.594798
A15: Azerbaijan | B15: 32.35 | C15: 54.91 | D15: 63.97 | E15: 51.1 | F15: 56.38 | G15: 29.73 | H15: =AVERAGE(B15:G15) -> 48.073333 | K15: Azerbaijan | L15: 12.264151 | M15: 50.471699 | N15: 18.00948 | O15: 29.245283 | P15: 49.056602 | Q15: 9.3137255 | R15: 28.060157
A16: Bahamas | B16: 69.11 | C16: 65.63 | D16: 83.48 | E16: 62.41 | F16: 53.97 | G16: 69.32 | H16: =AVERAGE(B16:G16) -> 67.32 | K16: Bahamas, The | L16: 88.20755 | M16: 61.792454 | N16: 84.834122 | O16: 55.660378 | P16: 51.886791 | Q16: 74.019608 | R16: 69.40015
A17: Bahrain | B17: 53.72 | C17: 60.95 | D17: 59.77 | E17: 61.59 | F17: 72.76 | G17: 30.7 | H17: =AVERAGE(B17:G17) -> 56.581667 | K17: Bahrain | L17: 59.433964 | M17: 74.528305 | N17: 29.383886 | O17: 65.56604 | P17: 83.962265 | Q17: 11.274509 | R17: 54.024828
A18: Bangladesh | B18: 28.2 | C18: 43.24 | D18: 49.11 | E18: 43.64 | F18: 39.35 | G18: 44.49 | H18: =AVERAGE(B18:G18) -> 41.338333 | K18: Bangladesh | L18: 14.622642 | M18: 26.886793 | N18: 15.639811 | O18: 33.490566 | P18: 18.867924 | Q18: 27.450981 | R18: 22.826453
A19: Barbados | B19: 72.8 | C19: 64.85 | D19: 88.05 | E19: 70.49 | F19: 62.28 | G19: 77.65 | H19: =AVERAGE(B19:G19) -> 72.686667 | K19: Barbados | L19: 89.622643 | M19: 64.15094 | N19: 93.83886 | O19: 62.264153 | P19: 67.452827 | Q19: 87.254906 | R19: 77.430721
A20: Belarus | B20: 36.5 | C20: 36 | D20: 62.57 | E20: 38.41 | F20: 33.82 | G20: 25.81 | H20: =AVERAGE(B20:G20) -> 38.851667 | K20: Belarus | L20: 26.886793 | M20: 15.094339 | N20: 18.483412 | O20: 11.320755 | P20: 7.5471697 | Q20: 3.9215686 | R20: 13.875673
... A23: Benin | B23: 43.78 | C23: 48.92 | D23: 58.62 | E23: 51.12 | F23: 50.4 | G23: 51.47 | H23: =AVERAGE(B23:G23) -> 50.718333 | K23: Benin | L23: 52.830189 | M23: 42.452831 | N23: 31.753555 | O23: 33.018867 | P23: 40.566036 | Q23: 40.196079 | R23: 40.13626
A24: Bermuda | B24: 71.84 | C24: 82.38 | D24: 84.54 | E24: 71.94 | F24: 66.04 | H24: =AVERAGE(B24:G24) -> 75.348 | K24: Bermuda | L24: 87.735847 | M24: 87.264153 | N24: 86.729858 | O24: 75 | P24: 79.245285 | R24: 83.195029
A25: Bhutan | B25: 77.76 | C25: 66.79 | D25: 90.02 | E25: 70.52 | F25: 53.89 | G25: 61.6 | H25: =AVERAGE(B25:G25) -> 70.096667 | K25: Bhutan | L25: 91.037735 | M25: 69.339622 | N25: 83.412323 | O25: 72.64151 | P25: 36.792454 | Q25: 54.901962 | R25: 68.020934
A26: Bolivia | B26: 24.13 | C26: 39.72 | D26: 62.74 | E26: 36.42 | F26: 34.46 | G26: 54.54 | H26: =AVERAGE(B26:G26) -> 42.001667 | K26: Bolivia | L26: 21.698112 | M26: 29.245283 | N26: 35.071091 | O26: 11.792453 | P26: 11.792453 | Q26: 39.215687 | R26: 24.802513
A27: Bosnia And Herzegovina | B27: 38.35 | C27: 42.6 | D27: 59.65 | E27: 53.03 | F27: 48.55 | G27: 53.03 | H27: =AVERAGE(B27:G27) -> 49.201667 | K27: Bosnia and Herzegovina | L27: 30.660378 | M27: 15.566038 | N27: 31.279621 | O27: 39.622643 | P27: 46.698112 | Q27: 38.235294 | R27: 33.677014
A28: Botswana | B28: 59.94 | C28: 61.23 | D28: 84.51 | E28: 63.26 | F28: 61.6 | G28: 64.99 | H28: =AVERAGE(B28:G28) -> 65.921667 | K28: Botswana | L28: 73.584908 | M28: 66.981133 | N28: 87.203789 | O28: 61.320755 | P28: 66.981133 | Q28: 62.745098 | R28: 69.802802
A29: Brazil | B29: 40.36 | C29: 51.61 | D29: 58.87 | E29: 50.63 | F29: 47.89 | G29: 65.47 | H29: =AVERAGE(B29:G29) -> 52.471667 | K29: Brazil | L29: 34.433964 | M29: 32.07547 | N29: 28.43602 | O29: 41.981133 | P29: 40.094341 | Q29: 59.803921 | R29: 39.470808
A30: Brunei | B30: 68.07 | C30: 70.61 | D30: 91.88 | E30: 69.73 | F30: 72.07 | G30: 40.22 | H30: =AVERAGE(B30:G30) -> 68.763333 | K30: Brunei Darussalam | L30: 88.679245 | M30: 90.094337 | N30: 96.682465 | O30: 79.245285 | P30: 80.660378 | Q30: 28.921568 | R30: 77.380546
A31: Bulgaria | B31: 42.22 | C31: 54.91 | D31: 69.9 | E31: 57.88 | F31: 61.34 | G31: 62.65 | H31: =AVERAGE(B31:G31) -> 58.15 | K31: Bulgaria | L31: 50 | M31: 53.301888 | N31: 55.450237 | O31: 53.773586 | P31: 65.56604 | Q31: 60.294117 | R31: 56.397645
A32: Burkina Faso | B32: 43.51 | C32: 36.15 | D32: 34.09 | E32: 43.48 | F32: 44.63 | G32: 35.63 | H32: =AVERAGE(B32:G32) -> 39.581667 | K32: Burkina Faso | L32: 49.528301 | M32: 21.226416 | N32: 5.6872039 | O32: 24.528301 | P32: 34.905659 | Q32: 25.490196 | R32: 26.894346
A33: Burundi | B33: 17 | C33: 26.7 | D33: 43.99 | E33: 35.02 | F33: 40.55 | G33: 29.49 | H33: =AVERAGE(B33:G33) -> 32.125 | K33: Burundi | L33: 3.3018868 | M33: 11.320755 | N33: 12.796208 | O33: 10.849056 | P33: 15.566038 | Q33: 11.764706 | R33: 10.933108
A34: Cambodia | B34: 22.56 | C34: 44.14 | D34: 71.47 | E34: 41.35 | F34: 45.4 | G34: 27.51 | H34: =AVERAGE(B34:G34) -> 42.071667 | K34: Cambodia | L34: 9.4339619 | M34: 38.207546 | N34: 47.867298 | O34: 23.584906 | P34: 25.471699 | Q34: 12.745098 | R34: 26.218418
A35: Cameroon | B35: 23.75 | C35: 36.07 | D35: 35.96 | E35: 38.97 | F35: 41.95 | G35: 34.68 | H35: =AVERAGE(B35:G35) -> 35.23 | K35: Cameroon | L35: 13.207547 | M35: 17.452829 | N35: 11.374408 | O35: 16.509434 | P35: 19.339622 | Q35: 19.607843 | R35: 16.248614
A36: Canada | B36: 80.21 | C36: 88.31 | D36: 79.8 | E36: 82.97 | F36: 80.3 | G36: 85.16 | H36: =AVERAGE(B36:G36) -> 82.791667 | K36: Canada | L36: 94.811317 | M36: 91.981133 | N36: 76.303314 | O36: 90.094337 | P36: 94.811317 | Q36: 95.098038 | R36: 90.516576
... A68: French Guiana | B68: 72.14 | C68: 80.32 | D68: 75.05 | E68: 74.18 | F68: 74.28 | G68: 78.16 | H68: =AVERAGE(B68:G68) -> 75.688333 | K68: France | L68: 83.962265 | M68: 83.018867 | N68: 55.924171 | O68: 84.905663 | P68: 85.377357 | Q68: 86.764709 | R68: 79.992172
A69: French Polynesia | B69: 44.06 | D69: 75.7 | E69: 69.33 | G69: 73.82 | H69: =AVERAGE(B69:G69) -> 65.7275 | K69: French Guiana | L69: 80.188683 | M69: 89.15094 | N69: 53.08057 | O69: 83.962265 | P69: 83.490562 | Q69: 91.666664 | R69: 80.256614
A70: Gabon | B70: 32.4 | C70: 41.06 | D70: 67.65 | E70: 41.77 | F70: 42.93 | G70: 42.56 | H70: =AVERAGE(B70:G70) -> 44.728333 | K70: Gabon | L70: 17.924528 | M70: 23.113207 | N70: 33.649288 | O70: 20.754717 | P70: 25 | Q70: 24.019608 | R70: 24.076891
A71: Gambia, The | B71: 37.74 | C71: 43.5 | D71: 66.23 | E71: 52.12 | F71: 44.4 | G71: 53.9 | H71: =AVERAGE(B71:G71) -> 49.648333 | K71: Gambia, The | L71: 46.226414 | M71: 29.716982 | N71: 45.971565 | O71: 38.207546 | P71: 28.301888 | Q71: 45.588234 | R71: 39.002105
A72: Georgia | B72: 45.22 | C72: 59.53 | D72: 56.93 | E72: 60.2 | F72: 66.23 | G72: 51.14 | H72: =AVERAGE(B72:G72) -> 56.541667 | K72: Georgia | L72: 71.226418 | M72: 77.830185 | N72: 33.175354 | O72: 55.188679 | P72: 79.71698 | Q72: 48.039215 | R72: 60.862805
A73: Germany | B73: 81.85 | C73: 82.84 | D73: 69.26 | E73: 85.07 | F73: 76.43 | G73: 86.03 | H73: =AVERAGE(B73:G73) -> 80.246667 | K73: Germany | L73: 94.339622 | M73: 85.377357 | N73: 66.350708 | O73: 92.92453 | P73: 91.981133 | Q73: 94.607841 | R73: 87.596865
A74: Ghana | B74: 45.79 | C74: 55.1 | D74: 67.15 | E74: 58.61 | F74: 52.32 | G74: 64.33 | H74: =AVERAGE(B74:G74) -> 57.216667 | K74: Ghana | L74: 51.415092 | M74: 47.169811 | N74: 45.497631 | O74: 49.528301 | P74: 45.28302 | Q74: 60.784313 | R74: 49.946362
A75: Greece | B75: 53.1 | C75: 58.93 | D75: 70.46 | E75: 63.33 | F75: 62.66 | G75: 73.55 | H75: =AVERAGE(B75:G75) -> 63.671667 | K75: Greece | L75: 58.018867 | M75: 57.547169 | N75: 54.028435 | O75: 57.07547 | P75: 70.754715 | Q75: 79.411766 | R75: 62.80607
A76: Greenland | B76: 77.9 | C76: 79.32 | D76: 79.45 | E76: 84.78 | F76: 73.92 | G76: 83.79 | H76: =AVERAGE(B76:G76) -> 79.86 | K76: Greenland | L76: 82.07547 | M76: 77.35849 | N76: 98.104263 | O76: 95.28302 | P76: 86.79245 | Q76: 91.666664 | R76: 88.546726
A77: Grenada | B77: 58.22 | C77: 52.45 | D77: 87.31 | E77: 68.21 | F77: 55.04 | G77: 66.59 | H77: =AVERAGE(B77:G77) -> 64.636667 | K77: Grenada | L77: 68.396225 | M77: 50.943398 | N77: 86.25592 | O77: 69.339622 | P77: 61.792454 | Q77: 71.07843 | R77: 67.967675
A78: Guam | B78: 71.84 | C78: 77.18 | D78: 86.48 | E78: 74.72 | F78: 61.94 | H78: =AVERAGE(B78:G78) -> 74.432 | K78: Guam | L78: 87.735847 | M78: 73.113205 | N78: 78.199051 | O78: 81.603775 | P78: 68.396225 | R78: 77.809621
A79: Guatemala | B79: 29.41 | C79: 36.46 | D79: 61.88 | E79: 41.63 | F79: 49.7 | G79: 51.54 | H79: =AVERAGE(B79:G79) -> 45.103333 | K79: Guatemala | L79: 14.150944 | M79: 18.396227 | N79: 36.966824 | O79: 15.566038 | P79: 41.509434 | Q79: 33.333332 | R79: 26.6538
A80: Guinea | B80: 26.56 | C80: 33.95 | D80: 52.78 | E80: 38.73 | F80: 39.12 | G80: 36.13 | H80: =AVERAGE(B80:G80) -> 37.878333 | K80: Guinea | L80: 20.283018 | M80: 16.981133 | N80: 16.113745 | O80: 14.150944 | P80: 13.207547 | Q80: 17.647058 | R80: 16.397241
A81: Guinea-Bissau | B81: 19.81 | C81: 22.25 | D81: 56.31 | E81: 37.73 | F81: 34.27 | G81: 37.99 | H81: =AVERAGE(B81:G81) -> 34.726667 | K81: Guinea-Bissau | L81: 12.735849 | M81: 8.0188675 | N81: 34.123222 | O81: 7.0754719 | P81: 9.9056606 | Q81: 36.274509 | R81: 18.022264
A82: Guyana | B82: 40.43 | C82: 55.36 | D82: 69.18 | E82: 53.48 | F82: 48.5 | G82: 58.87 | H82: =AVERAGE(B82:G82) -> 54.303333 | K82: Guyana | L82: 40.566036 | M82: 39.622643 | N82: 43.601894 | O82: 40.566036 | P82: 31.603773 | Q82: 52.941177 | R82: 41.483593
A83: Haiti | B83: 16.97 | C83: 10.57 | D83: 41.43 | E83: 31.98 | F83: 29.5 | G83: 35.06 | H83: =AVERAGE(B83:G83) -> 27.585 | K83: Haiti | L83: 6.1320753 | M83: 0.94339621 | N83: 10.42654 | O83: 7.5471697 | P83: 8.4905663 | Q83: 16.17647 | R83: 8.2860363
A84: Honduras | B84: 22.89 | C84: 40.36 | D84: 57.96 | E84: 39.62 | F84: 44.57 | G84: 46.81 | H84: =AVERAGE(B84:G84) -> 42.035 | K84: Honduras | L84: 15.094339 | M84: 22.64151 | N84: 27.962086 | O84: 15.094339 | P84: 32.07547 | Q84: 35.294117 | R84: 24.693644
A85: Hong Kong (China) | B85: 81.05 | C85: 83.84 | D85: 79.19 | E85: 74.14 | F85: 83.33 | G85: 48.13 | H85: =AVERAGE(B85:G85) -> 74.946667 | K85: Hong Kong (China) | L85: 93.396225 | M85: 92.92453 | N85: 69.668243 | O85: 87.735847 | P85: 93.867928 | Q85: 37.254902 | R85: 79.141279
A86: Hungary | B86: 48.09 | C86: 61.96 | D86: 74.53 | E86: 62.18 | F86: 60.04 | G86: 57.07 | H86: =AVERAGE(B86:G86) -> 60.645 | K86: Hungary | L86: 54.71698 | M86: 62.735847 | N86: 72.037918 | O86: 63.207546 | P86: 62.735847 | Q86: 59.313725 | R86: 62.457977
A87: Iceland | B87: 84.83 | C87: 83.98 | D87: 88.76 | E87: 85.18 | F87: 73.84 | G87: 82.74 | H87: =AVERAGE(B87:G87) -> 83.221667 | K87: Iceland | L87: 91.981133 | M87: 93.396225 | N87: 95.260666 | O87: 96.698112 | P87: 87.264153 | Q87: 94.117645 | R87: 93.119656
A88: India | B88: 42.41 | C88: 62.62 | D88: 54.96 | E88: 56.51 | F88: 52.58 | G88: 54.93 | H88: =AVERAGE(B88:G88) -> 54.001667 | K88: India | L88: 41.509434 | M88: 67.92453 | N88: 21.327015 | O88: 56.132076 | P88: 47.169811 | Q88: 51.470589 | R88: 47.588909
A89: Indonesia | B89: 37.68 | C89: 57.56 | D89: 52.66 | E89: 54.44 | F89: 57.33 | G89: 54.67 | H89: =AVERAGE(B89:G89) -> 52.39 | K89: Indonesia | L89: 36.320755 | M89: 69.811317 | N89: 28.909952 | O89: 46.698112 | P89: 60.849056 | Q89: 52.450981 | R89: 49.173362
A90: Iran | B90: 25.02 | C90: 34.8 | D90: 35.98 | E90: 38.57 | F90: 29.24 | G90: 27.86 | H90: =AVERAGE(B90:G90) -> 31.911667 | K90: Iran | L90: 10.377358 | M90: 14.150944 | N90: 8.0568724 | O90: 16.037735 | P90: 4.2452831 | Q90: 7.8431373 | R90: 10.118555
... A122: Marshall Islands | B122: 55.2 | C122: 45.12 | D122: 92.2 | E122: 74.33 | F122: 42.91 | G122: 74.65 | H122: =AVERAGE(B122:G122) -> 64.068333 | K122: Malta | L122: 58.490566 | M122: 65.56604 | N122: 77.251183 | O122: 75.471695 | P122: 74.056602 | Q122: 76.960785 | R122: 71.299479
A123: Martinique | B123: 59.25 | C123: 71.9 | D123: 67.96 | E123: 71.94 | F123: 66.04 | H123: =AVERAGE(B123:G123) -> 67.418 | K123: Marshall Islands | L123: 64.15094 | M123: 54.71698 | N123: 93.364929 | O123: 73.113205 | P123: 36.320755 | Q123: 86.274513 | R123: 67.99022
A124: Mauritania | B124: 28.97 | C124: 36.85 | D124: 54.14 | E124: 45.31 | F124: 43.06 | G124: 41.17 | H124: =AVERAGE(B124:G124) -> 41.583333 | K124: Martinique | L124: 70.754715 | M124: 73.113205 | N124: 61.611374 | O124: 75 | P124: 79.245285 | R124: 71.944916
A125: Mauritius | B125: 55.96 | C125: 69.94 | D125: 81.93 | E125: 69.77 | F125: 71.54 | G125: 68.84 | H125: =AVERAGE(B125:G125) -> 69.663333 | K125: Mauritania | L125: 22.64151 | M125: 24.528301 | N125: 26.066351 | O125: 27.35849 | P125: 15.094339 | Q125: 30.392157 | R125: 24.346858
A126: Mexico | B126: 29.03 | C126: 48.65 | D126: 54.95 | E126: 39.38 | F126: 51.47 | G126: 52.55 | H126: =AVERAGE(B126:G126) -> 46.005 | K126: Mauritius | L126: 65.56604 | M126: 75 | N126: 74.881516 | O126: 77.830185 | P126: 82.547173 | Q126: 66.666664 | R126: 73.748596
A127: Micronesia, Fed. Sts. | B127: 61.57 | C127: 50.85 | D127: 92.2 | E127: 74.63 | F127: 42.12 | G127: 74.33 | H127: =AVERAGE(B127:G127) -> 65.95 | K127: Mexico | L127: 17.452829 | M127: 43.396225 | N127: 22.748816 | O127: 24.056604 | P127: 46.226414 | Q127: 42.156864 | R127: 32.672959
A128: Moldova | B128: 42.92 | C128: 56.73 | D128: 63.64 | E128: 56.12 | F128: 54.59 | G128: 62.54 | H128: =AVERAGE(B128:G128) -> 56.09 | K128: Micronesia, Fed. Sts. | L128: 78.301888 | M128: 59.433964 | N128: 89.573463 | O128: 72.169815 | P128: 30.660378 | Q128: 83.823532 | R128: 68.99384
A129: Monaco | B129: 71.84 | C129: 87.62 | D129: 87.57 | E129: 85.8 | F129: 82.41 | G129: 74.93 | H129: =AVERAGE(B129:G129) -> 81.695 | K129: Moldova | L129: 46.698112 | M129: 44.339622 | N129: 20.379147 | O129: 47.169811 | P129: 54.71698 | Q129: 55.882355 | R129: 44.864338
A130: Mongolia | B130: 38.99 | C130: 48.14 | D130: 75.54 | E130: 56.72 | F130: 54.65 | G130: 62.04 | H130: =AVERAGE(B130:G130) -> 56.013333 | K130: Monaco | L130: 87.735847 | M130: 99.056602 | N130: 93.364929 | O130: 91.509438 | P130: 89.622643 | Q130: 69.607841 | R130: 88.482883
A131: Montenegro | B131: 49.57 | C131: 61.98 | D131: 73.46 | E131: 62.06 | F131: 59.1 | G131: 65.04 | H131: =AVERAGE(B131:G131) -> 61.868333 | K131: Mongolia | L131: 35.377357 | M131: 33.962265 | N131: 67.298576 | O131: 43.867924 | P131: 45.754719 | Q131: 56.372547 | R131: 47.105565
A132: Morocco | B132: 37.9 | C132: 55.96 | D132: 56.1 | E132: 53.01 | F132: 55.19 | G132: 45.02 | H132: =AVERAGE(B132:G132) -> 50.53 | K132: Montenegro | L132: 51.886791 | M132: 59.905659 | N132: 48.815166 | O132: 52.35849 | P132: 64.15094 | Q132: 58.333332 | R132: 55.908396
A133: Mozambique | B133: 25.95 | C133: 35.8 | D133: 36.59 | E133: 39.23 | F133: 42.41 | G133: 41.18 | H133: =AVERAGE(B133:G133) -> 36.86 | K133: Morocco | L133: 33.018867 | M133: 50 | N133: 29.857821 | O133: 48.584908 | P133: 50.943398 | Q133: 34.313725 | R133: 41.119786
A134: Myanmar | B134: 21.71 | C134: 19.23 | D134: 28.53 | E134: 29.49 | F134: 30.44 | G134: 19.36 | H134: =AVERAGE(B134:G134) -> 24.793333 | K134: Mozambique | L134: 22.169811 | M134: 25.943396 | N134: 11.848341 | O134: 17.452829 | P134: 24.528301 | Q134: 31.862745 | R134: 22.300904
A135: Namibia | B135: 51.03 | C135: 54.4 | D135: 78.59 | E135: 64.83 | F135: 56.74 | G135: 64.58 | H135: =AVERAGE(B135:G135) -> 61.695 | K135: Myanmar | L135: 11.792453 | M135: 3.7735848 | N135: 4.7393365 | O135: 6.1320753 | P135: 7.0754719 | Q135: 2.4509804 | R135: 5.9939836
A136: Nepal | B136: 32.45 | C136: 36.59 | D136: 57.84 | E136: 53.58 | F136: 44.25 | G136: 54.64 | H136: =AVERAGE(B136:G136) -> 46.558333 | K136: Namibia | L136: 58.962265 | M136: 52.830189 | N136: 63.507111 | O136: 64.622643 | P136: 51.415092 | Q136: 66.176468 | R136: 59.585628
A137: Netherlands | B137: 85.85 | C137: 87.96 | D137: 74.97 | E137: 86.2 | F137: 80.24 | G137: 86.84 | H137: =AVERAGE(B137:G137) -> 83.676667 | K137: Nauru | L137: 69.811317 | M137: 48.584908 | N137: 82.938385 | O137: 53.301888 | P137: 52.35849 | Q137: 68.627449 | R137: 62.603739
A138: New Caledonia | B138: 50.81 | D138: 70.73 | E138: 62.87 | G138: 58.99 | H138: =AVERAGE(B138:G138) -> 60.85 | K138: Nepal | L138: 33.962265 | M138: 21.698112 | N138: 39.336494 | O138: 34.905659 | P138: 27.35849 | Q138: 46.07843 | R138: 33.889908
A139: New Zealand | B139: 86.1 | C139: 90.68 | D139: 86.31 | E139: 85.92 | F139: 87.41 | G139: 87.27 | H139: =AVERAGE(B139:G139) -> 87.281667 | K139: Netherlands | L139: 96.226418 | M139: 95.754715 | N139: 68.720383 | O139: 94.339622 | P139: 97.169815 | Q139: 96.568626 | R139: 91.463263
A140: Nicaragua | B140: 20.21 | C140: 34.05 | D140: 65.43 | E140: 32.49 | F140: 39.26 | G140: 25.39 | H140: =AVERAGE(B140:G140) -> 36.138333 | K140: Netherlands Antilles (former)
A141: Niger | B141: 33.18 | C141: 34.65 | D141: 34.63 | E141: 40.06 | F141: 42.31 | G141: 36.75 | H141: =AVERAGE(B141:G141) -> 36.93 | K141: New Zealand | L141: 98.584908 | M141: 92.452827 | N141: 96.208534 | O141: 95.754715 | P141: 98.584908 | Q141: 99.509804 | R141: 96.849283
A142: Nigeria | B142: 26.5 | C142: 33.65 | D142: 35.14 | E142: 42.95 | F142: 44.38 | G142: 45.6 | H142: =AVERAGE(B142:G142) -> 38.036667 | K142: Nicaragua | L142: 7.0754719 | M142: 13.207547 | N142: 42.180096 | O142: 9.4339619 | P142: 20.283018 | Q142: 10.294118 | R142: 17.079035
A143: Niue | B143: 38.93 | C143: 37.87 | D143: 83.34 | E143: 57.69 | F143: 44.78 | G143: 54.11 | H143: =AVERAGE(B143:G143) -> 52.786667 | K143: Niger | L143: 31.603773 | M143: 28.773584 | N143: 8.5308056 | O143: 25 | P143: 20.754717 | Q143: 29.90196 | R143: 24.09414
A144: North Korea | B144: 16.73 | C144: 25.24 | D144: 67.07 | E144: 34.14 | F144: 21.27 | G144: 18.72 | H144: =AVERAGE(B144:G144) -> 30.528333 | K144: Nigeria | L144: 16.981133 | M144: 20.283018 | N144: 7.5829382 | O144: 20.283018 | P144: 16.981133 | Q144: 32.35294 | R144: 19.077363
A145: North Macedonia | B145: 42.04 | C145: 56.37 | D145: 72.18 | E145: 56.3 | F145: 63.32 | G145: 61.28 | H145: =AVERAGE(B145:G145) -> 58.581667 | K145: Niue | L145: 49.056602 | M145: 83.962265 | O145: 31.132076 | P145: 55.188679 | R145: 54.834906
A146: Norway | B146: 86.98 | C146: 90 | D146: 84.52 | E146: 90.61 | F146: 82.79 | G146: 91.21 | H146: =AVERAGE(B146:G146) -> 87.685 | K146: North Macedonia | L146: 42.452831 | M146: 49.056602 | N146: 51.184834 | O146: 45.28302 | P146: 66.037735 | Q146: 53.431374 | R146: 51.241066
A147: Oman | B147: 58.19 | C147: 60.13 | D147: 76.04 | E147: 66.9 | F147: 67.42 | G147: 37.37 | H147: =AVERAGE(B147:G147) -> 61.008333 | K147: Norway | L147: 99.056602 | M147: 97.64151 | N147: 77.725121 | O147: 99.056602 | P147: 93.396225 | Q147: 100 | R147: 94.479343
A148: Pakistan | B148: 26.49 | C148: 39.94 | D148: 31.43 | E148: 41.06 | F148: 39.69 | G148: 37.02 | H148: =AVERAGE(B148:G148) -> 35.938333 | K148: Oman | L148: 60.849056 | M148: 62.264153 | N148: 65.876778 | O148: 70.28302 | P148: 66.509438 | Q148: 21.078432 | R148: 57.810146
A149: Palau | B149: 58.4 | C149: 54.47 | D149: 88.37 | E149: 77.93 | F149: 63.16 | G149: 76.35 | H149: =AVERAGE(B149:G149) -> 69.78 | K149: Pakistan | L149: 18.867924 | M149: 30.660378 | N149: 6.6350713 | O149: 21.226416 | P149: 19.811321 | Q149: 23.039215 | R149: 20.040054
A150: Palestine | B150: 36.26 | C150: 25.38 | D150: 32.13 | E150: 42.79 | F150: 48.5 | G150: 35.9 | H150: =AVERAGE(B150:G150) -> 36.826667 | K150: Palau | L150: 69.811317 | M150: 67.452827 | N150: 89.573463 | O150: 80.660378 | P150: 65.094337 | Q150: 83.823532 | R150: 76.069309
A151: Panama | B151: 36.8 | C151: 56.78 | D151: 69.87 | E151: 53.64 | F151: 53.41 | G151: 66.5 | H151: =AVERAGE(B151:G151) -> 56.166667 | K151: Panama | L151: 28.301888 | M151: 42.92453 | N151: 52.606636 | O151: 40.094341 | P151: 55.660378 | Q151: 64.215683 | R151: 47.300576
A152: Papua New Guinea | B152: 32.33 | C152: 37.8 | D152: 56.04 | E152: 49.2 | F152: 44.93 | G152: 53.4 | H152: =AVERAGE(B152:G152) -> 45.616667 | K152: Papua New Guinea | L152: 27.35849 | M152: 22.169811 | N152: 27.014217 | O152: 29.716982 | P152: 27.830189 | Q152: 47.058823 | R152: 30.191419
A153: Paraguay | B153: 27.73 | C153: 47.68 | D153: 68.04 | E153: 48.23 | F153: 54.99 | G153: 55.24 | H153: =AVERAGE(B153:G153) -> 50.318333 | K153: Paraguay | L153: 16.037735 | M153: 34.433964 | N153: 49.289101 | O153: 28.773584 | P153: 50.471699 | Q153: 48.529411 | R153: 37.922582
A154: Peru | B154: 32.81 | C154: 49.4 | D154: 56.91 | E154: 47.78 | F154: 57.55 | G154: 56.73 | H154: =AVERAGE(B154:G154) -> 50.196667 | K154: Peru | L154: 25.471699 | M154: 33.018867 | N154: 24.170616 | O154: 30.188679 | P154: 60.377357 | Q154: 49.509804 | R154: 37.122837
A155: Philippines | B155: 36.47 | C155: 56.33 | D155: 50.97 | E155: 50.87 | F155: 58.46 | G155: 53.03 | H155: =AVERAGE(B155:G155) -> 51.021667 | K155: Philippines | L155: 32.547169 | M155: 58.018867 | N155: 23.696682 | O155: 37.264153 | P155: 57.547169 | Q155: 46.568626 | R155: 42.607111
A156: Poland | B156: 65.16 | C156: 68.64 | D156: 77.76 | E156: 68.01 | F156: 69.07 | G156: 72.75 | H156: =AVERAGE(B156:G156) -> 70.231667 | K156: Poland | L156: 68.867928 | M156: 66.509438 | N156: 63.981041 | O156: 65.094337 | P156: 76.415092 | Q156: 67.647057 | R156: 68.085815
A157: Portugal | B157: 63.62 | C157: 73.26 | D157: 77.91 | E157: 75.88 | F157: 65.15 | G157: 81.06 | H157: =AVERAGE(B157:G157) -> 72.813333 | K157: Portugal | L157: 74.056602 | M157: 80.188683 | N157: 70.616112 | O157: 83.490562 | P157: 75.471695 | Q157: 88.235291 | R157: 78.676491
... A162: Russia | B162: 28.21 | C162: 42.09 | D162: 49.05 | E162: 37.66 | F162: 34.92 | G162: 31.29 | H162: =AVERAGE(B162:G162) -> 37.203333 | K162: Rwanda | L162: 73.113205 | M162: 65.094337 | N162: 49.763035 | O162: 56.603775 | P162: 56.132076 | Q162: 24.509804 | R162: 54.202705
A163: Rwanda | B163: 60.88 | C163: 59.74 | D163: 67.75 | E163: 60.25 | F163: 59.88 | G163: 43.75 | H163: =AVERAGE(B163:G163) -> 58.708333 | K163: Réunion | L163: 70.754715 | M163: 73.113205 | N163: 48.341232 | O163: 75 | P163: 79.245285 | R163: 69.290887
A164: Réunion | B164: 59.25 | C164: 71.9 | D164: 67.74 | E164: 66.92 | F164: 66.04 | H164: =AVERAGE(B164:G164) -> 66.37 | K164: Samoa | L164: 75.943398 | M164: 68.867928 | N164: 90.521324 | O164: 79.71698 | P164: 42.92453 | Q164: 80.882355 | R164: 73.142752
A165: Samoa | B165: 61.32 | C165: 56.49 | D165: 89 | E165: 76.11 | F165: 54.2 | G165: 74.53 | H165: =AVERAGE(B165:G165) -> 68.608333 | K165: San Marino | L165: 87.735847 | M165: 87.264153 | N165: 93.364929 | O165: 91.509438 | P165: 79.245285 | Q165: 89.705879 | R165: 88.137589
A166: San Marino | B166: 71.84 | C166: 70.09 | D166: 90.6 | E166: 82.44 | F166: 70.13 | G166: 80.49 | H166: =AVERAGE(B166:G166) -> 77.598333 | K166: Saudi Arabia | L166: 66.509438 | M166: 78.773582 | N166: 39.810425 | O166: 62.735847 | P166: 68.867928 | Q166: 8.8235292 | R166: 54.253458
A167: Saudi Arabia | B167: 64.29 | C167: 67.48 | D167: 65.91 | E167: 63.14 | F167: 67.02 | G167: 25.99 | H167: =AVERAGE(B167:G167) -> 58.971667 | K167: Senegal | L167: 56.603775 | M167: 54.245281 | N167: 41.232227 | O167: 42.92453 | P167: 39.150944 | Q167: 51.960785 | R167: 47.686257
A168: Senegal | B168: 51.07 | C168: 57.47 | D168: 62.69 | E168: 55.46 | F168: 50.97 | G168: 60.67 | H168: =AVERAGE(B168:G168) -> 56.388333 | K168: Serbia | L168: 38.207546 | M168: 51.886791 | N168: 44.549763 | O168: 51.415092 | P168: 56.603775 | Q168: 44.607841 | R168: 47.878468
...

Sheet Pollution
A1: Country | B1: PM25_2023 | C1: Year | D1: Active (tab 1 uses col B). PM2.5 mean annual exposure, micrograms per m3, population-weighted, modelled (satellite + ground monitors). Source: Global Burden of Disease Study 2023, IHME, via World Bank (2026), processed by Our World in Data. Lower = better. | F1: Country | G1: Pollution_2026MY | H1: Exp Pollution Index | J1: Country | K1: Pollution_2025 | L1: Exp Pollution Index | M1: Numbeo. Active: 2026 Mid-Year (A:B). | N1: Numbeo pollution (perception survey) 2026 Mid-Year and 2025 - kept for reference, no longer used.
A2: Greenland | B2: 1.64 | C2: 2023 | F2: Cameroon | G2: 91.9 | H2: 166 | J2: Cameroon | K2: 93.7 | L2: 169.8
A3: Northern Mariana Islands | B3: 2.68 | C3: 2023 | F3: Myanmar | G3: 89.6 | H3: 161.8 | J3: Myanmar | K3: 89.8 | L3: 162.2
A4: Guam | B4: 3.47 | C4: 2023 | F4: Lebanon | G4: 89.2 | H4: 159.5 | J4: Lebanon | K4: 89.4 | L4: 159.8
A5: Micronesia (country) | B5: 3.52 | C5: 2023 | F5: Mongolia | G5: 88 | H5: 160.9 | J5: Nigeria | K5: 88.2 | L5: 157.5
A6: Kiribati | B6: 3.87 | C6: 2023 | F6: Nigeria | G6: 87.2 | H6: 155.7 | J6: Mongolia | K6: 87.8 | L6: 160.4
A7: Marshall Islands | B7: 4.1 | C7: 2023 | F7: Ghana | G7: 86.3 | H7: 154.5 | J7: Ghana | K7: 87 | L7: 155.8
A8: American Samoa | B8: 4.33 | C8: 2023 | F8: Bangladesh | G8: 85.2 | H8: 152.2 | J8: Bangladesh | K8: 85.6 | L8: 153
A9: Finland | B9: 4.57 | C9: 2023 | F9: Afghanistan | G9: 84.4 | H9: 150.5 | J9: Afghanistan | K9: 84.4 | L9: 150.5
A10: Samoa | B10: 4.58 | C10: 2023 | F10: Nepal | G10: 84.4 | H10: 150.1 | J10: Vietnam | K10: 84.2 | L10: 150.4
A11: Bermuda | B11: 4.63 | C11: 2023 | F11: Vietnam | G11: 83.7 | H11: 149.4 | J11: Nepal | K11: 84.2 | L11: 149.6
A12: Tonga | B12: 4.69 | C12: 2023 | F12: Peru | G12: 82.7 | H12: 147.2 | J12: Egypt | K12: 82.7 | L12: 146.8
A13: Nauru | B13: 4.84 | C13: 2023 | F13: Egypt | G13: 82.6 | H13: 146.6 | J13: Peru | K13: 82.5 | L13: 146.7
... A114: Venezuela | B114: 19.2 | C114: 2023 | F114: Sweden | G114: 17.1 | H114: 27.1 | J114: Finland | K114: 11.9 | L114: 19.9
A115: Serbia | B115: 19.34 | C115: 2023 | F115: Iceland | G115: 17.1 | H115: 28.7
A116: Cambodia | B116: 19.43 | C116: 2023 | F116: Austria | G116: 16.3 | H116: 27.1
A117: Kazakhstan | B117: 19.6 | C117: 2023 | F117: Estonia | G117: 15.7 | H117: 25.4
A118: Bulgaria | B118: 19.68 | C118: 2023 | F118: Finland | G118: 10.9 | H118: 19.1
A119: Angola | B119: 19.91 | C119: 2023
A120: Libya | B120: 20.01 | C120: 2023
A121: Kyrgyzstan | B121: 20.12 | C121: 2023
A122: Tanzania | B122: 20.17 | C122: 2023
A123: Cape Verde | B123: 20.19 | C123: 2023
A124: Zambia | B124: 20.24 | C124: 2023
A125: Kenya | B125: 20.25 | C125: 2023
A126: Ivory Coast | B126: 20.39 | C126: 2023
A127: Nicaragua | B127: 20.42 | C127: 2023
A128: Indonesia | B128: 20.84 | C128: 2023
A129: Jamaica | B129: 21.65 | C129: 2023
A130: North Korea | B130: 21.78 | C130: 2023
... A208: Qatar | B208: 107.76 | C208: 2023

Sheet Climate
A1: Country | B1: Climate_hours | C1: GeoRank: comfortable outdoor hours per year (static, does not change by year). Collected for the old 106-country list only. | E1: Country | F1: Climate_2025 | G1: Old: Numbeo climate score (0-100), no longer used.
A2: Peru | B2: 4029 | E2: Venezuela | F2: 99.9
A3: Kenya | B3: 3871 | E3: Kenya | F3: 99.8
A4: Zimbabwe | B4: 3684 | E4: Costa Rica | F4: 99.5
A5: South Africa | B5: 3533 | E5: Ecuador | F5: 98.7
A6: Colombia | B6: 3521 | E6: Colombia | F6: 98.4
A7: Morocco | B7: 3506 | E7: Argentina | F7: 98.3
A8: Uganda | B8: 3481 | E8: Uruguay | F8: 98
A9: Chile | B9: 3478 | E9: Peru | F9: 97.7
A10: Mexico | B10: 3462 | E10: Malta | F10: 97.4
A11: Australia | B11: 3315 | E11: Brazil | F11: 97.4
A12: Argentina | B12: 3231 | E12: Portugal | F12: 97.3
A13: Portugal | B13: 3176 | E13: New Zealand | F13: 95.5
... A89: Singapore | B89: 1186 | E89: Kuwait | F89: 20.2
A90: Vietnam | B90: 1139
A91: Panama | B91: 1115
A92: Indonesia | B92: 1023
A93: Iceland | B93: 1012
A94: Philippines | B94: 928
A95: Malaysia | B95: 660
A96: Thailand | B96: 660

Sheet English
A1: Country/Region | B1: Proficiency Band | C1: Score | D1: Band points | E1: Source: https://www.ef.com/wwen/epi/ EF EPI 2025. Tab 1 uses Score (col C). Native-English countries are set to 700 directly on tab 1. | G1: Country/Region | H1: Proficiency Band | I1: Score | J1: Band points | K1: English_2024 (old)
A2: Netherlands | B2: Very high proficiency | C2: 624 | D2: =IF(LEFT(B2,9)="Very high",100,IF(LEFT(B2,4)="High",80,IF(LEFT(B2,8)="Moderate",60,IF(LEFT(B2,3)="Low",40,IF(LEFT(B2,8)="Very low",20))))) -> 100 | G2: Netherlands | H2: Very high proficiency | I2: 636
A3: Croatia | B3: Very high proficiency | C3: 617 | D3: =IF(LEFT(B3,9)="Very high",100,IF(LEFT(B3,4)="High",80,IF(LEFT(B3,8)="Moderate",60,IF(LEFT(B3,3)="Low",40,IF(LEFT(B3,8)="Very low",20))))) -> 100 | G3: Norway | H3: Very high proficiency | I3: 610
A4: Austria | B4: Very high proficiency | C4: 616 | D4: =IF(LEFT(B4,9)="Very high",100,IF(LEFT(B4,4)="High",80,IF(LEFT(B4,8)="Moderate",60,IF(LEFT(B4,3)="Low",40,IF(LEFT(B4,8)="Very low",20))))) -> 100 | G4: Singapore | H4: Very high proficiency | I4: 609
A5: Germany | B5: Very high proficiency | C5: 615 | D5: =IF(LEFT(B5,9)="Very high",100,IF(LEFT(B5,4)="High",80,IF(LEFT(B5,8)="Moderate",60,IF(LEFT(B5,3)="Low",40,IF(LEFT(B5,8)="Very low",20))))) -> 100 | G5: Sweden | H5: Very high proficiency | I5: 608
A6: Norway | B6: Very high proficiency | C6: 613 | D6: =IF(LEFT(B6,9)="Very high",100,IF(LEFT(B6,4)="High",80,IF(LEFT(B6,8)="Moderate",60,IF(LEFT(B6,3)="Low",40,IF(LEFT(B6,8)="Very low",20))))) -> 100 | G6: Croatia | H6: Very high proficiency | I6: 607
A7: Portugal | B7: Very high proficiency | C7: 612 | D7: =IF(LEFT(B7,9)="Very high",100,IF(LEFT(B7,4)="High",80,IF(LEFT(B7,8)="Moderate",60,IF(LEFT(B7,3)="Low",40,IF(LEFT(B7,8)="Very low",20))))) -> 100 | G7: Portugal | H7: Very high proficiency | I7: 605
A8: Denmark | B8: Very high proficiency | C8: 611 | D8: =IF(LEFT(B8,9)="Very high",100,IF(LEFT(B8,4)="High",80,IF(LEFT(B8,8)="Moderate",60,IF(LEFT(B8,3)="Low",40,IF(LEFT(B8,8)="Very low",20))))) -> 100 | G8: Denmark | H8: Very high proficiency | I8: 603
A9: Sweden | B9: Very high proficiency | C9: 609 | D9: =IF(LEFT(B9,9)="Very high",100,IF(LEFT(B9,4)="High",80,IF(LEFT(B9,8)="Moderate",60,IF(LEFT(B9,3)="Low",40,IF(LEFT(B9,8)="Very low",20))))) -> 100 | G9: Greece | H9: Very high proficiency | I9: 602
A10: Belgium | B10: Very high proficiency | C10: 608 | D10: =IF(LEFT(B10,9)="Very high",100,IF(LEFT(B10,4)="High",80,IF(LEFT(B10,8)="Moderate",60,IF(LEFT(B10,3)="Low",40,IF(LEFT(B10,8)="Very low",20))))) -> 100 | G10: Austria | H10: Very high proficiency | I10: 600
A11: Slovakia | B11: Very high proficiency | C11: 606 | D11: =IF(LEFT(B11,9)="Very high",100,IF(LEFT(B11,4)="High",80,IF(LEFT(B11,8)="Moderate",60,IF(LEFT(B11,3)="Low",40,IF(LEFT(B11,8)="Very low",20))))) -> 100 | G11: Germany | H11: High Proficiency | I11: 598
A12: Romania | B12: Very high proficiency | C12: 605 | D12: =IF(LEFT(B12,9)="Very high",100,IF(LEFT(B12,4)="High",80,IF(LEFT(B12,8)="Moderate",60,IF(LEFT(B12,3)="Low",40,IF(LEFT(B12,8)="Very low",20))))) -> 100 | G12: South Africa | H12: High Proficiency | I12: 594
A13: Finland | B13: Very high proficiency | C13: 603 | D13: =IF(LEFT(B13,9)="Very high",100,IF(LEFT(B13,4)="High",80,IF(LEFT(B13,8)="Moderate",60,IF(LEFT(B13,3)="Low",40,IF(LEFT(B13,8)="Very low",20))))) -> 100 | G13: Romania | H13: High proficiency | I13: 593
... A117: Thailand | B117: Very low proficiency | C117: 402 | D117: =IF(LEFT(B117,9)="Very high",100,IF(LEFT(B117,4)="High",80,IF(LEFT(B117,8)="Moderate",60,IF(LEFT(B117,3)="Low",40,IF(LEFT(B117,8)="Very low",20))))) -> 20 | G117: Yemen | H117: Very low proficiency | I117: 394
A118: Yemen | B118: Very low proficiency | C118: 402 | D118: =IF(LEFT(B118,9)="Very high",100,IF(LEFT(B118,4)="High",80,IF(LEFT(B118,8)="Moderate",60,IF(LEFT(B118,3)="Low",40,IF(LEFT(B118,8)="Very low",20))))) -> 20
A119: Democratic Republic of the Congo | B119: Very low proficiency | C119: 400 | D119: =IF(LEFT(B119,9)="Very high",100,IF(LEFT(B119,4)="High",80,IF(LEFT(B119,8)="Moderate",60,IF(LEFT(B119,3)="Low",40,IF(LEFT(B119,8)="Very low",20))))) -> 20
A120: Somalia | B120: Very low proficiency | C120: 398 | D120: =IF(LEFT(B120,9)="Very high",100,IF(LEFT(B120,4)="High",80,IF(LEFT(B120,8)="Moderate",60,IF(LEFT(B120,3)="Low",40,IF(LEFT(B120,8)="Very low",20))))) -> 20
A121: Togo | B121: Very low proficiency | C121: 397 | D121: =IF(LEFT(B121,9)="Very high",100,IF(LEFT(B121,4)="High",80,IF(LEFT(B121,8)="Moderate",60,IF(LEFT(B121,3)="Low",40,IF(LEFT(B121,8)="Very low",20))))) -> 20
A122: Libya | B122: Very low proficiency | C122: 395 | D122: =IF(LEFT(B122,9)="Very high",100,IF(LEFT(B122,4)="High",80,IF(LEFT(B122,8)="Moderate",60,IF(LEFT(B122,3)="Low",40,IF(LEFT(B122,8)="Very low",20))))) -> 20
A123: Ivory Coast | B123: Very low proficiency | C123: 393 | D123: =IF(LEFT(B123,9)="Very high",100,IF(LEFT(B123,4)="High",80,IF(LEFT(B123,8)="Moderate",60,IF(LEFT(B123,3)="Low",40,IF(LEFT(B123,8)="Very low",20))))) -> 20
A124: Cambodia | B124: Very low proficiency | C124: 390 | D124: =IF(LEFT(B124,9)="Very high",100,IF(LEFT(B124,4)="High",80,IF(LEFT(B124,8)="Moderate",60,IF(LEFT(B124,3)="Low",40,IF(LEFT(B124,8)="Very low",20))))) -> 20
A125: Singapore | B125: Very high proficiency (2024, carried over: not in EF 2025) | C125: 609 | D125: =IF(LEFT(B125,9)="Very high",100,IF(LEFT(B125,4)="High",80,IF(LEFT(B125,8)="Moderate",60,IF(LEFT(B125,3)="Low",40,IF(LEFT(B125,8)="Very low",20))))) -> 100
A126: Luxembourg | B126: High proficiency (2024, carried over: not in EF 2025) | C126: 576 | D126: =IF(LEFT(B126,9)="Very high",100,IF(LEFT(B126,4)="High",80,IF(LEFT(B126,8)="Moderate",60,IF(LEFT(B126,3)="Low",40,IF(LEFT(B126,8)="Very low",20))))) -> 80

Sheet Openness
A1: Country | B1: Openness_2024 | C1: InterNations Expat Insider 2024, Ease of Settling In rank (1=best). Kept as active: 2026 edition ranks only 31 countries. | E1: Country | F1: Openness_2026 | G1: Expat Insider 2026 (31 countries) - stored for reference, not used.
A2: Costa Rica | B2: 1 | E2: Mexico | F2: 1
A3: Mexico | B3: 2 | E3: Panama | F3: 2
A4: Philippines | B4: 3 | E4: Thailand | F4: 3
A5: Indonesia | B5: 4 | E5: Brazil | F5: 4
A6: Brazil | B6: 5 | E6: United Arab Emirates | F6: 5
A7: Thailand | B7: 6 | E7: Spain | F7: 6
A8: Panama | B8: 7 | E8: Portugal | F8: 7
A9: Colombia | B9: 8 | E9: Ireland | F9: 8
A10: Kenya | B10: 9 | E10: United States | F10: 9
A11: Greece | B11: 10 | E11: South Africa | F11: 10
A12: Spain | B12: 11 | E12: Australia | F12: 11
A13: Oman | B13: 12 | E13: Singapore | F13: 12
... A32: Belgium | B32: 31 | E32: Norway | F32: 31
A33: Malta | B33: 32
A34: Italy | B34: 33
A35: France | B35: 34
A36: Japan | B36: 35
A37: South Korea | B37: 36
A38: Poland | B38: 37
A39: Luxembourg | B39: 38
A40: Canada | B40: 39
A41: Turkey | B41: 40
A42: Netherlands | B42: 41
A43: United Kingdom | B43: 42
A44: Chile | B44: 43
... A54: Kuwait | B54: 53

Sheet Scenic
A1: Country | B1: Rank | C1: source https://www.usnews.com/news/best-countries/rankings/scenic?utm_source=chatgpt.com
A2: Greece | B2: 1 | C2: 2024 data
A3: New Zealand | B3: 2
A4: Italy | B4: 3
A5: Switzerland | B5: 4
A6: Spain | B6: 5
A7: Thailand | B7: 6
A8: Norway | B8: 7
A9: Iceland | B9: 8
A10: Australia | B10: 9
A11: Austria | B11: 10
A12: Ireland | B12: 11
A13: Brazil | B13: 12
A14: Portugal | B14: 13
... A90: Iran | B90: 89

Sheet Disaster
A1: Country | B1: Rank | C1: W | D1: E | E1: V | F1: StormRiskIndex | G1: StormRiskRank | H1: Disaster_2026: WorldRiskReport 2026, p.58-61. W = WorldRiskIndex (used by tab 1, col C). E = Exposure, V = Vulnerability. | J1: WRI.Country | K1: ISO3.Code | L1: W | M1: E | N1: V | O1: S | P1: C | Q1: A | R1: Disaster_2024 (old). Korea rows corrected (PRK was labelled South Korea).
A2: Philippines | B2: 1 | C2: 46.69 | D2: 40.76 | E2: 53.49 | F2: 69.27 | G2: 1 | J2: Philippines | K2: PHL | L2: 46.91 | M2: 39.99 | N2: 55.03 | O2: 51.16 | P2: 58.07 | Q2: 56.1
A3: India | B3: 2 | C3: 44.97 | D3: 40.83 | E3: 49.54 | F3: 11.99 | G3: 14 | J3: Indonesia | K3: IDN | L3: 41.13 | M3: 39.89 | N3: 42.4 | O3: 32.37 | P3: 51.01 | Q3: 46.17
A4: Indonesia | B4: 3 | C4: 44.63 | D4: 39.78 | E4: 50.08 | F4: 11.69 | G4: 15 | J4: India | K4: IND | L4: 40.96 | M4: 35.99 | N4: 46.62 | O4: 37.15 | P4: 54.01 | Q4: 50.49
A5: Colombia | B5: 4 | C5: 39.8 | D5: 31.59 | E5: 50.14 | F5: 10.88 | G5: 17 | J5: Colombia | K5: COL | L5: 37.81 | M5: 31.54 | N5: 45.33 | O5: 39.3 | P5: 49.28 | Q5: 48.1
A6: Mexico | B6: 5 | C6: 39.18 | D6: 50.69 | E6: 30.28 | F6: 47.4 | G6: 2 | J6: Mexico | K6: MEX | L6: 35.93 | M6: 50.08 | N6: 25.78 | O6: 30.03 | P6: 11.97 | Q6: 47.68
A7: Myanmar | B7: 6 | C7: 37.51 | D7: 22.44 | E7: 62.7 | F7: 13.39 | G7: 13 | J7: Myanmar | K7: MMR | L7: 35.85 | M7: 22.43 | N7: 57.31 | O7: 51.43 | P7: 58.75 | Q7: 62.29
A8: Mozambique | B8: 7 | C8: 30.92 | D8: 14.69 | E8: 65.09 | F8: 13.72 | G8: 12 | J8: Mozambique | K8: MOZ | L8: 34.44 | M8: 18.1 | N8: 65.53 | O8: 65.79 | P8: 63.13 | Q8: 67.75
A9: Russia | B9: 8 | C9: 30.58 | D9: 28.37 | E9: 32.97 | F9: 8.86 | G9: 23 | J9: Russia | K9: RUS | L9: 28.12 | M9: 28.35 | N9: 27.89 | O9: 15.31 | P9: 40.03 | Q9: 35.38
A10: China | B10: 9 | C10: 29.54 | D10: 71.06 | E10: 12.28 | F10: 30.38 | G10: 6 | J10: Bangladesh | K10: BGD | L10: 27.73 | M10: 16.57 | N10: 46.39 | O10: 35.5 | P10: 57.92 | Q10: 48.54
A11: Somalia | B11: 10 | C11: 29.12 | D11: 11.94 | E11: 71 | F11: 0.84 | G11: 71 | J11: Pakistan | K11: PAK | L11: 27.02 | M11: 13.11 | N11: 55.69 | O11: 42.64 | P11: 63.1 | Q11: 64.18
A12: Honduras | B12: 11 | C12: 27.68 | D12: 21.89 | E12: 34.99 | F12: 10.04 | G12: 18 | J12: Peru | K12: PER | L12: 27.01 | M12: 16.65 | N12: 43.82 | O12: 36.32 | P12: 46.06 | Q12: 50.3
A13: Papua New Guinea | B13: 12 | C13: 27.64 | D13: 21.2 | E13: 36.04 | F13: 2.33 | G13: 53 | J13: Papua New Guinea | K13: PNG | L13: 26.35 | M13: 18.84 | N13: 36.84 | O13: 57.46 | P13: 13.59 | Q13: 64.04
... A194: Monaco | B194: 193 | C194: 0.21 | D194: 0.02 | E194: 2.28 | F194: 0.15 | G194: 193 | J194: Monaco | K194: MCO | L194: 0.18 | M194: 0.02 | N194: 1.57 | O194: 1.68 | P194: 0.44 | Q194: 5.25

Sheet LifeExp60
A1: Country | B1: LifeExp60_2024 | C1: Female | D1: Male | E1: Life expectancy at age 60 (remaining years), 2024. Source: UN World Population Prospects, via World Bank Gender Data Portal (SP.DYN.LE60.FE.IN / .MA.IN). Col B = average of female and male; MALE COLUMN EMPTY for now (first export was scrambled) -> B currently = female only. Paste correct male values in col D and B updates automatically.
A2: Monaco | B2: =AVERAGE(C2:D2) -> 29.859 | C2: 29.859
A3: Hong Kong (China) | B3: =AVERAGE(C3:D3) -> 29.811 | C3: 29.811
A4: Japan | B4: =AVERAGE(C4:D4) -> 29.482 | C4: 29.482
A5: Gibraltar | B5: =AVERAGE(C5:D5) -> 28.572 | C5: 28.572
A6: San Marino | B6: =AVERAGE(C6:D6) -> 28.519 | C6: 28.519
A7: South Korea | B7: =AVERAGE(C7:D7) -> 28.35 | C7: 28.35
A8: France | B8: =AVERAGE(C8:D8) -> 28.253 | C8: 28.253
A9: French Polynesia | B9: =AVERAGE(C9:D9) -> 28.201 | C9: 28.201
A10: Spain | B10: =AVERAGE(C10:D10) -> 27.982 | C10: 27.982
A11: Andorra | B11: =AVERAGE(C11:D11) -> 27.89 | C11: 27.89
A12: Bermuda | B12: =AVERAGE(C12:D12) -> 27.86 | C12: 27.86
A13: Singapore | B13: =AVERAGE(C13:D13) -> 27.825 | C13: 27.825
... A217: Nigeria | B217: =AVERAGE(C217:D217) -> 15.473 | C217: 15.473

Sheet CGT
A1: Country | B1: CGT | C1: Providing headline number | D1: https://taxsummaries.pwc.com/quick-charts/capital-gains-tax-cgt-rates
A2: Switzerland | B2: 0
A3: Luxembourg
A4: United States
A5: Singapore
A6: Iceland
A7: Denmark
A8: Australia
A9: Hong Kong (China)
A10: Netherlands
A11: Norway
A12: United Kingdom
A13: United Arab Emirates
A14: New Zealand
... A107: Nigeria

Sheet Sheet1
A1: Country | B1: Col_2026MY | C1: Sal_2026 | E1: Country | F1: Col_2025 | G1: Numbeo Cost of Living Plus Rent Index. Active: 2026 Mid-Year (A:B). Older year kept for comparison.
A2: Bermuda | B2: 122.1 | C2: =VLOOKUP(A2, Salary!A:B, 2, FALSE()) -> #N/A | E2: Us Virgin Islands | F2: 75.4
A3: Cayman Islands | B3: 99 | C3: =VLOOKUP(A3, Salary!A:B, 2, FALSE()) -> #N/A | E3: Switzerland | F3: 74.8
A4: Switzerland | B4: 81.5 | C4: =VLOOKUP(A4, Salary!A:B, 2, FALSE()) -> 7112.01 | E4: Singapore | F4: 73.7
A5: Singapore | B5: 80.5 | C5: =VLOOKUP(A5, Salary!A:B, 2, FALSE()) -> 4469.53 | E5: Bahamas | F5: 66.1
A6: Bahamas | B6: 77.2 | C6: =VLOOKUP(A6, Salary!A:B, 2, FALSE()) -> #N/A | E6: Iceland | F6: 65.9
A7: Iceland | B7: 74.8 | C7: =VLOOKUP(A7, Salary!A:B, 2, FALSE()) -> 4742.72 | E7: Hong Kong (China) | F7: 65.7
A8: Jersey | B8: 71.6 | C8: =VLOOKUP(A8, Salary!A:B, 2, FALSE()) -> #N/A | E8: Guernsey | F8: 57.1
A9: Hong Kong (China) | B9: 68.5 | C9: =VLOOKUP(A9, Salary!A:B, 2, FALSE()) -> 3266.5 | E9: Luxembourg | F9: 54.8
A10: Turkmenistan | B10: 66.1 | C10: =VLOOKUP(A10, Salary!A:B, 2, FALSE()) -> #N/A | E10: United States | F10: 54.3
A11: Solomon Islands | B11: 65.7 | C11: =VLOOKUP(A11, Salary!A:B, 2, FALSE()) -> #N/A | E11: Papua New Guinea | F11: 53.7
A12: Israel | B12: 64.8 | C12: =VLOOKUP(A12, Salary!A:B, 2, FALSE()) -> 3678.8 | E12: Ireland | F12: 50.6
A13: Guernsey | B13: 64.5 | C13: =VLOOKUP(A13, Salary!A:B, 2, FALSE()) -> #N/A | E13: Norway | F13: 49.4
... A140: Tanzania | B140: 17.5 | C140: =VLOOKUP(A140, Salary!A:B, 2, FALSE()) -> #N/A | E140: Pakistan | F140: 11.2
A141: Syria | B141: 17.3 | C141: =VLOOKUP(A141, Salary!A:B, 2, FALSE()) -> #N/A
A142: Indonesia | B142: 17 | C142: =VLOOKUP(A142, Salary!A:B, 2, FALSE()) -> 260.19
A143: Nigeria | B143: 16.6 | C143: =VLOOKUP(A143, Salary!A:B, 2, FALSE()) -> #N/A
A144: Madagascar | B144: 16.5 | C144: =VLOOKUP(A144, Salary!A:B, 2, FALSE()) -> #N/A
A145: Algeria | B145: 16.1 | C145: =VLOOKUP(A145, Salary!A:B, 2, FALSE()) -> 295.6
A146: Iran | B146: 15.1 | C146: =VLOOKUP(A146, Salary!A:B, 2, FALSE()) -> 246.03
A147: Bangladesh | B147: 13.4 | C147: =VLOOKUP(A147, Salary!A:B, 2, FALSE()) -> 224.13
A148: Egypt | B148: 13.4 | C148: =VLOOKUP(A148, Salary!A:B, 2, FALSE()) -> 138.65
A149: Nepal | B149: 13.2 | C149: =VLOOKUP(A149, Salary!A:B, 2, FALSE()) -> 211.67
A150: Afghanistan | B150: 12.9 | C150: =VLOOKUP(A150, Salary!A:B, 2, FALSE()) -> #N/A
A151: Libya | B151: 12.7 | C151: =VLOOKUP(A151, Salary!A:B, 2, FALSE()) -> #N/A
A152: Pakistan | B152: 12.4 | C152: =VLOOKUP(A152, Salary!A:B, 2, FALSE()) -> 191.7
A153: India | B153: 11.6 | C153: =VLOOKUP(A153, Salary!A:B, 2, FALSE()) -> 416.21

Sheet Sheet2
A1: Country | B1: Sal | C1: Col_2025 | D1: % Sal Germ | E1: % Sal Col
A2: Switzerland | B2: 6862.91 | C2: =VLOOKUP(A2, Sheet1!A:B, 2, FALSE()) -> 81.5 | D2: =(B2-B$18)*100/B$18 -> 108.78439 | E2: =(C2-C$18)*100/C$18 -> 73.404255
A3: Luxembourg | B3: 5379.43 | C3: =VLOOKUP(A3, Sheet1!A:B, 2, FALSE()) -> 64.2 | D3: =(B3-B$18)*100/B$18 -> 63.65376 | E3: =(C3-C$18)*100/C$18 -> 36.595745
A4: United States | B4: 4269.48 | C4: =VLOOKUP(A4, Sheet1!A:B, 2, FALSE()) -> 54.8 | D4: =(B4-B$18)*100/B$18 -> 29.886708 | E4: =(C4-C$18)*100/C$18 -> 16.595745
A5: Singapore | B5: 4106.34 | C5: =VLOOKUP(A5, Sheet1!A:B, 2, FALSE()) -> 80.5 | D5: =(B5-B$18)*100/B$18 -> 24.92364 | E5: =(C5-C$18)*100/C$18 -> 71.276596
A6: Iceland | B6: 4076.16 | C6: =VLOOKUP(A6, Sheet1!A:B, 2, FALSE()) -> 74.8 | D6: =(B6-B$18)*100/B$18 -> 24.0055 | E6: =(C6-C$18)*100/C$18 -> 59.148936
A7: Denmark | B7: 4005.27 | C7: =VLOOKUP(A7, Sheet1!A:B, 2, FALSE()) -> 54.8 | D7: =(B7-B$18)*100/B$18 -> 21.848875 | E7: =(C7-C$18)*100/C$18 -> 16.595745
A8: Australia | B8: 3945.23 | C8: =VLOOKUP(A8, Sheet1!A:B, 2, FALSE()) -> 53.9 | D8: =(B8-B$18)*100/B$18 -> 20.02233 | E8: =(C8-C$18)*100/C$18 -> 14.680851
A9: Hong Kong (China) | B9: 3852.5 | C9: =VLOOKUP(A9, Sheet1!A:B, 2, FALSE()) -> 68.5 | D9: =(B9-B$18)*100/B$18 -> 17.201285 | E9: =(C9-C$18)*100/C$18 -> 45.744681
A10: Netherlands | B10: 3829.17 | C10: =VLOOKUP(A10, Sheet1!A:B, 2, FALSE()) -> 56 | D10: =(B10-B$18)*100/B$18 -> 16.491537 | E10: =(C10-C$18)*100/C$18 -> 19.148936
A11: Norway | B11: 3645.41 | C11: =VLOOKUP(A11, Sheet1!A:B, 2, FALSE()) -> 59.3 | D11: =(B11-B$18)*100/B$18 -> 10.901165 | E11: =(C11-C$18)*100/C$18 -> 26.170213
A12: United Kingdom | B12: 3572.87 | C12: =VLOOKUP(A12, Sheet1!A:B, 2, FALSE()) -> 50.8 | D12: =(B12-B$18)*100/B$18 -> 8.6943427 | E12: =(C12-C$18)*100/C$18 -> 8.0851064
A13: United Arab Emirates | B13: 3520.47 | C13: =VLOOKUP(A13, Sheet1!A:B, 2, FALSE()) -> 46.8 | D13: =(B13-B$18)*100/B$18 -> 7.1002227 | E13: =(C13-C$18)*100/C$18 -> -0.42553191
... A107: Nigeria | B107: 122.75 | C107: =VLOOKUP(A107, Sheet1!A:B, 2, FALSE()) -> 16.6 | D107: =(B107-B$18)*100/B$18 -> -96.265683 | E107: =(C107-C$18)*100/C$18 -> -64.680851

Sheet Salary
A1: Country | B1: Sal_2026 | D1: Country | E1: Sal_2025 | F1: Numbeo average monthly net salary. Not used by the tool.
A2: Switzerland | B2: 7112.01 | D2: Switzerland | E2: 6862.91
A3: Luxembourg | B3: 5462.17 | D3: Luxembourg | E3: 5379.43
A4: Iceland | B4: 4742.72 | D4: United States | E4: 4269.48
A5: Singapore | B5: 4469.53 | D5: Singapore | E5: 4106.34
A6: Norway | B6: 4401.35 | D6: Iceland | E6: 4076.16
A7: United States | B7: 4307.38 | D7: Denmark | E7: 4005.27
A8: Denmark | B8: 4109.82 | D8: Australia | E8: 3945.23
A9: Qatar | B9: 4090.05 | D9: Hong Kong (China) | E9: 3852.5
A10: Australia | B10: 3984.31 | D10: Netherlands | E10: 3829.17
A11: Netherlands | B11: 3787.83 | D11: Norway | E11: 3645.41
A12: Israel | B12: 3678.8 | D12: United Kingdom | E12: 3572.87
A13: United Kingdom | B13: 3528.19 | D13: United Arab Emirates | E13: 3520.47
... A103: Cuba | B103: 35.51 | D103: Ghana | E103: 189.88
D104: Pakistan | E104: 181.6
D105: Uganda | E105: 177.32
D106: Egypt | E106: 147.61
D107: Nigeria | E107: 122.75

Sheet Notes
A1: Variable | B1: Active data | C1: Older data kept | D1: Notes
A2: Cost of Living | B2: Numbeo 2026 Mid-Year, COL Plus Rent (Sheet1 A:B) | C2: 2025 | D2: Defines the country list: all 152 countries with COL data.
A3: Safety | B3: UNODC homicide rate (via Our World in Data), converted to 0-100 safety score (log scale) | C3: Numbeo perceived safety 2026 Mid-Year & 2025 | D3: Switched from perception (Numbeo) to objective homicide rate. Tab 1 header stays "Safety", higher = safer, so script needs no change. Some latest years are old (Thailand, Vietnam, Cambodia 2011; Syria 2010). No data: Taiwan, Senegal, Kyrgyzstan, Madagascar, Libya, DR Congo, Ivory Coast. Jersey/Guernsey use Channel Islands 2010 figure.
A4: Healthcare | B4: Numbeo 2026 Mid-Year | C4: 2025
A5: Political Stability | B5: World Bank WGI 2026 release, year 2025, governance score 0-100, avg of 6 | C5: 2023 (percentile ranks) | D5: Scales differ between years. 2023 Korea rows corrected (old tool used North Korea values for South Korea).
A6: Pollution | B6: PM2.5 mean annual exposure 2023 (GBD 2023 / IHME via World Bank, OWID) | C6: Numbeo pollution 2026 Mid-Year & 2025 | D6: Switched from Numbeo perception survey to modelled PM2.5 (objective, population-weighted). No data: Hong Kong, Taiwan, Macao, Kosovo, Cayman Islands, Jersey, Guernsey, Isle of Man, Gibraltar.
A7: Climate | B7: GeoRank comfortable outdoor hours/yr | C7: Numbeo 2025 climate score | D7: Hours only collected for the old 106 countries.
A8: English Proficiency | B8: EF EPI 2025 score | C8: EF 2024 | D8: Native-English countries = 700 on tab 1 (US, AU, UK, NZ, IE, CA, PR). Singapore 609 & Luxembourg 576 carried over from 2024 (absent from EF 2025).
A9: Openness | B9: Expat Insider 2024 rank (53 countries) | C9: 2026 stored (31 countries) | D9: 2026 kept for reference only.
A10: Natural Scenery | B10: US News 2024 rank | C10: - | D10: Unchanged.
A11: Natural Disaster | B11: WorldRiskReport 2026, EXPOSURE (col D) - changed from WorldRiskIndex W | C11: 2024 | D11: Switched to Exposure: WRI also includes societal vulnerability, which double-counts governance/healthcare already in the index. Only UN members: Hong Kong, Taiwan, Puerto Rico, Kosovo have no value. 2024 Korea rows corrected.
A12: Life Expectancy at 60 | B12: UN WPP via World Bank, life expectancy at 60, 2024 (avg of female & male) | C12: - | D12: NEW 10th variable (Oct 2026). Remaining years at age 60: more relevant to retirees than life expectancy at birth. Male data pending re-download (first export scrambled); currently female only. No data: Taiwan, Jersey, Guernsey.
A13: Salary (Sal_2025 column) | B13: Numbeo 2026 | C13: 2025 | D13: Removed from tab 1 (Oct 29): unused by the tool, but its blanks were counted by the "more than 2 N/A" filter. Kept on the Salary tab.
A15: TO DO (next session)
A16: 1. Integrate file with script; test tool (check #N/A handling, and whether the >2 N/A filter counts Sal column).
A17: 2. Value-for-money: fit a curve (not a line) of COL vs suitability; rank countries by distance above it.
A18: 3. Default view: only countries with enough data; click to reveal sparse ones. Show coverage (x/9) on hover.
A19: 4. User weights 0-3 per factor - check if easy in script.
A20: 5. Safety: DONE - homicide rate added (log-scaled score).
A21: 6. DONE - Life Expectancy at 60 added (male data still to paste in).
A22: 7. Air quality: DONE - PM2.5 replaces Numbeo pollution.
A23: 8. Check UN DESA expat share of population (possible Openness replacement).
A24: 9. Look into LGBTQ+ legal equality (Equaldex), possibly as optional filter.
A25: 10. Think about future heat (days >35C by 2050).
A26: 11. Methods page: update sources, record Exposure switch, normalisation note (compare overall ranks, not individual factor scores, across versions), known limitations: Numbeo small samples (e.g. India salary -49%), country averages vs city variation, perception-based sources (scenery, openness).
A27: 12. Visa: write content first; decide tool integration later.
